[
  {
    "title": "۲۰۷ tu5p   صفر",
    "subtitle": "۰ کیلومتر",
    "price": "۱۵,۳۰۰,۰۰۰ تومان",
    "city": "مشهد",
    "location": "مشکینی (شهرک غرب)",
    "token": "QadW3Jl1",
    "url": "https://divar.ir/v/QadW3Jl1",
    "image": "https://s100.divarcdn.com/static/photo/neda/webp_thumbnail/h4Z8ghFUfmEJSXU3KPSDPA/12805e55-7534-4f99-99c0-22dd12d0923d.webp"
  },
  {
    "title": "حواله",
    "subtitle": "۰ کیلومتر",
    "price": "۸۰۰,۰۰۰,۰۰۰ تومان",
    "city": "مشهد",
    "location": "آزادشهر",
    "token": "QaSCg8jz",
    "url": "https://divar.ir/v/QaSCg8jz",
    "image": "https://s100.divarcdn.com/static/photo/neda/webp_thumbnail/pDKpo6V-n4bTEEaZ-A2biA/9cd57ac7-ba4b-484e-a9c1-eb0f3128b951.webp"
  },
  {
    "title": "نیسان امیتیس پلاس",
    "subtitle": "۰ کیلومتر",
    "price": "۵,۰۵۰,۰۰۰,۰۰۰ تومان",
    "city": "مشهد",
    "location": "سلام",
    "token": "QadO3tYd",
    "url": "https://divar.ir/v/QadO3tYd",
    "image": "https://s100.divarcdn.com/static/photo/neda/webp_thumbnail/6WEKMugrTTMJlAA_QJAVDg/1abb60f8-d0a4-4db9-b73f-21b43f1c5785.webp"
  },
  {
    "title": "تویوتا کمری هیبریدی ژاپنی صفر",
    "subtitle": "۰ کیلومتر",
    "price": "۱۰,۰۰۰,۰۰۰,۰۰۰ تومان",
    "city": "مشهد",
    "location": "نوفل لوشاتو",
    "token": "Qad-mvn8",
    "url": "https://divar.ir/v/Qad-mvn8",
    "image": "https://s100.divarcdn.com/static/photo/neda/webp_thumbnail/n3636qKtmXtzHn2CG4HQww/812557d4-60c1-49dd-9063-47b451925415.webp"
  },
  {
    "title": "۲۰۷ اتومات پانا",
    "subtitle": "۰ کیلومتر",
    "price": "۱,۸۸۰,۰۰۰,۰۰۰ تومان",
    "city": "مشهد",
    "location": "هنرستان",
    "token": "Qad6G0A_",
    "url": "https://divar.ir/v/Qad6G0A_",
    "image": "https://s100.divarcdn.com/static/photo/neda/webp_thumbnail/Z478I4kKp9pa07-12Cpcfw/a9108a98-036a-43af-82e1-8ff5f10020bf.webp"
  },
  {
    "title": "کوییک gxr L صفر فول آپشن - رینگ اسپرت",
    "subtitle": "۰ کیلومتر",
    "price": "۹۷۰,۰۰۰,۰۰۰ تومان",
    "city": "مشهد",
    "location": "حرم مطهر رضوی",
    "token": "QaUGCvG1",
    "url": "https://divar.ir/v/QaUGCvG1",
    "image": "https://s100.divarcdn.com/static/photo/neda/webp_thumbnail/oxB38FloWrKAS45BmV3aLg/34c22b17-a5dc-41ef-ba5f-55358bcfa581.webp"
  },
  {
    "title": "اشکودا سوپرب 2024 مشکی صفر",
    "subtitle": "۰ کیلومتر",
    "price": "۴,۶۰۰,۰۰۰,۰۰۰ تومان",
    "city": "مشهد",
    "location": "فلسطین",
    "token": "Qad2mLO3",
    "url": "https://divar.ir/v/Qad2mLO3",
    "image": "https://s100.divarcdn.com/static/photo/neda/webp_thumbnail/01ziH_qPXfqVRbCwpCwqJA/370639a9-81b1-4712-888f-e6f005ada974.jpg.webp"
  },
  {
    "title": "حواله نیسان آلتیما قیمت 5/888",
    "subtitle": "۰ کیلومتر",
    "price": "۱۵۰,۰۰۰,۰۰۰ تومان",
    "city": "مشهد",
    "location": "هفت تیر (حافظ)",
    "token": "QadyGwnY",
    "url": "https://divar.ir/v/QadyGwnY",
    "image": "https://s100.divarcdn.com/static/photo/neda/webp_thumbnail/CGo_kFnx3WmTp-EdtZHDvA/73b445bc-fa16-4974-95c2-2660bd0ade29.webp"
  },
  {
    "title": "اتیما ۲۰۲۵ خشک",
    "subtitle": "۰ کیلومتر",
    "price": "۷,۰۰۰,۰۰۰,۰۰۰ تومان",
    "city": "مشهد",
    "location": "حرم مطهر رضوی",
    "token": "QadyGSPG",
    "url": "https://divar.ir/v/QadyGSPG",
    "image": "https://s100.divarcdn.com/static/photo/neda/webp_thumbnail/LxUFTc_vawwk4veEYhAcoA/c3eca785-9743-4ea3-9c7e-0b439c0feba7.webp"
  },
  {
    "title": "شاهین g 1403 صفر",
    "subtitle": "۰ کیلومتر",
    "price": "۱,۶۰۰,۰۰۰,۰۰۰ تومان",
    "city": "مشهد",
    "location": "حسابی جنوبی (شهرک غرب)",
    "token": "QaduGs95",
    "url": "https://divar.ir/v/QaduGs95",
    "image": "https://s100.divarcdn.com/static/photo/neda/webp_thumbnail/m5zupgvyTKMcBXnLyBX8Lg/41ec7066-9150-4cc3-abcf-ac55539d3c56.webp"
  },
  {
    "title": "پژو۲۰۷ صفرTu5p  سقف فلز ۱۴۰۴ سقف فلزمعاوضه هم دارم",
    "subtitle": "۰ کیلومتر",
    "price": "۱,۴۶۰,۰۰۰,۰۰۰ تومان",
    "city": "مشهد",
    "location": "شهید فرامرز عباسی",
    "token": "QacqQSMl",
    "url": "https://divar.ir/v/QacqQSMl",
    "image": "https://s100.divarcdn.com/static/photo/neda/webp_thumbnail/ETjt1ZSVdqTl87QdabAHhg/8b8549e7-70ef-45cb-9d1f-8840dfda07ce.webp"
  },
  {
    "title": "زامیاد اکستند دوگانه",
    "subtitle": "۰ کیلومتر",
    "price": "۱,۲۰۰,۰۰۰,۰۰۰ تومان",
    "city": "مشهد",
    "location": "شهرک لشکر (شهرک غرب)",
    "token": "Qada2BEG",
    "url": "https://divar.ir/v/Qada2BEG",
    "image": "https://s100.divarcdn.com/static/photo/neda/webp_thumbnail/OIGIMdOgw0XR8jdKH7Eg0Q/31cd332d-d702-4a5c-9a12-a0e1d1654651.webp"
  },
  {
    "title": "پارس نوا ال نودجدید",
    "subtitle": "۰ کیلومتر",
    "price": "۲,۴۵۰,۰۰۰,۰۰۰ تومان",
    "city": "مشهد",
    "location": "شریف",
    "token": "QadmmbA_",
    "url": "https://divar.ir/v/QadmmbA_",
    "image": "https://s100.divarcdn.com/static/photo/neda/webp_thumbnail/aS_57NyAcTlkQ-LULir1jA/e1a282b7-6929-4708-998a-ed132133ae25.webp"
  },
  {
    "title": "کوییک s صفر فوری فوری",
    "subtitle": "۰ کیلومتر",
    "price": "۹۰۵,۰۰۰,۰۰۰ تومان",
    "city": "مشهد",
    "location": "سرافرازان",
    "token": "QadaWqnh",
    "url": "https://divar.ir/v/QadaWqnh",
    "image": "https://s100.divarcdn.com/static/photo/neda/webp_thumbnail/h5WONB3W0hx6_U8_rFtzZg/83f0fb59-6bbf-437b-aca3-452943f37ec5.webp"
  },
  {
    "title": "۲۰۷پانا دنده tu5p",
    "subtitle": "۰ کیلومتر",
    "price": "۱,۵۶۰,۰۰۰,۰۰۰ تومان",
    "city": "مشهد",
    "location": "فدک",
    "token": "QaZSVGKX",
    "url": "https://divar.ir/v/QaZSVGKX",
    "image": "https://s100.divarcdn.com/static/photo/neda/webp_thumbnail/_0SBmrXXNFKZHQcXx94NKw/6a3b317f-d1fc-4c99-be92-08c98b18638b.webp"
  },
  {
    "title": "ساینا s صفر کیلومتر",
    "subtitle": "۰ کیلومتر",
    "price": "۹۴۰,۰۰۰,۰۰۰ تومان",
    "city": "مشهد",
    "location": "شهید مطهری",
    "token": "QadOG9aW",
    "url": "https://divar.ir/v/QadOG9aW",
    "image": "https://s100.divarcdn.com/static/photo/neda/webp_thumbnail/Pc8FXzBGdq9zpGWfxg1yiQ/8edea4ee-e587-4a2d-b107-836877aefaf7.webp"
  },
  {
    "title": "فولکس واگن id4 مدل ۲۰۲۵ صفر",
    "subtitle": "۰ کیلومتر",
    "price": "۵,۴۷۰,۰۰۰,۰۰۰ تومان",
    "city": "مشهد",
    "location": "شهید فرامرز عباسی",
    "token": "QaRm-Fmw",
    "url": "https://divar.ir/v/QaRm-Fmw",
    "image": "https://s100.divarcdn.com/static/photo/neda/webp_thumbnail/7nU8-fzqoQ19-_IPAmiLrw/773b495d-97d7-4eb7-9abd-8f77cef590fe.webp"
  },
  {
    "title": "تارا V1 Plus",
    "subtitle": "۰ کیلومتر",
    "price": "۸۰۰,۰۰۰,۰۰۰ تومان",
    "city": "مشهد",
    "location": "دانشجو",
    "token": "QadOmng8",
    "url": "https://divar.ir/v/QadOmng8",
    "image": "https://s100.divarcdn.com/static/photo/neda/webp_thumbnail/olaoaY9pGrUv_ssf6NJS5w/1526bb8f-60d1-4038-aacc-1fe6960927c6.webp"
  },
  {
    "title": "وانت اریسان ۲ مدل ۱۴۰۴",
    "subtitle": "۰ کیلومتر",
    "price": "۱,۰۰۰ تومان",
    "city": "مشهد",
    "location": "اقبال",
    "token": "QadK21rV",
    "url": "https://divar.ir/v/QadK21rV",
    "image": "https://s100.divarcdn.com/static/photo/neda/webp_thumbnail/yIZXdSzwdHfv50m1VliRgw/93f66e14-ab6d-46a7-a650-1aad918e63ae.webp"
  },
  {
    "title": "ساینا مانیتور دار صفر",
    "subtitle": "۰ کیلومتر",
    "price": "۹۵۰,۰۰۰,۰۰۰ تومان",
    "city": "مشهد",
    "location": "ثامن",
    "token": "QaSePXiz",
    "url": "https://divar.ir/v/QaSePXiz",
    "image": "https://s100.divarcdn.com/static/photo/neda/webp_thumbnail/TT9Qjup2o60O1VMJzwkbzg/7405d02d-888c-4511-acf9-75aa72c8529f.webp"
  },
  {
    "title": "سورن پلاس دریچه سیمی صفر",
    "subtitle": "۰ کیلومتر",
    "price": "۱,۳۷۰,۰۰۰,۰۰۰ تومان",
    "city": "مشهد",
    "location": "سید رضی",
    "token": "QadKGkXV",
    "url": "https://divar.ir/v/QadKGkXV",
    "image": "https://s100.divarcdn.com/static/photo/neda/webp_thumbnail/hWmSFM7hakDGBuEJGPrs6Q/074dca9b-2235-4235-8c51-617e525cd958.webp"
  },
  {
    "title": "جک جی 4 صفر j4",
    "subtitle": "۰ کیلومتر",
    "price": "۱,۸۲۰,۰۰۰,۰۰۰ تومان",
    "city": "مشهد",
    "location": "هفت تیر (آب و برق)",
    "token": "QaRe6gZH",
    "url": "https://divar.ir/v/QaRe6gZH",
    "image": "https://s100.divarcdn.com/static/photo/neda/webp_thumbnail/qAwwyHncfRCLq55tOCJM0Q/aaaccd94-1763-40bd-905f-cb0101f3bd71.webp"
  },
  {
    "title": "شاهین صفر اتوماتیک CVT",
    "subtitle": "۰ کیلومتر",
    "price": "۱,۸۰۰,۰۰۰,۰۰۰ تومان",
    "city": "مشهد",
    "location": "عبادی",
    "token": "QadCW4Hz",
    "url": "https://divar.ir/v/QadCW4Hz",
    "image": "https://s100.divarcdn.com/static/photo/neda/webp_thumbnail/_Olp8oH8rzcXu0yqweUM0w/482d59c6-1da0-43f6-835e-239e89112eaa.webp"
  },
  {
    "title": "دنا پلاس اتوماتیک یکماهه تحویل گرفتم",
    "subtitle": "۰ کیلومتر",
    "price": "۱,۹۸۰,۰۰۰,۰۰۰ تومان",
    "city": "مشهد",
    "location": "هفت تیر (آب و برق)",
    "token": "QadCWPT7",
    "url": "https://divar.ir/v/QadCWPT7",
    "image": "https://s100.divarcdn.com/static/photo/neda/webp_thumbnail/6D2mHDcsYWISa1q5ukrr7g/afc7d6bf-785f-433d-955c-978cde965eab.webp"
  },
  {
    "title": "۲۰۷ tu5p   صفر",
    "subtitle": "۰ کیلومتر",
    "price": "۱۵,۳۰۰,۰۰۰ تومان",
    "city": "مشهد",
    "location": "مشکینی (شهرک غرب)",
    "token": "QadW3Jl1",
    "url": "https://divar.ir/v/QadW3Jl1",
    "image": "https://s100.divarcdn.com/static/photo/neda/webp_thumbnail/h4Z8ghFUfmEJSXU3KPSDPA/12805e55-7534-4f99-99c0-22dd12d0923d.webp"
  },
  {
    "title": "حواله",
    "subtitle": "۰ کیلومتر",
    "price": "۸۰۰,۰۰۰,۰۰۰ تومان",
    "city": "مشهد",
    "location": "آزادشهر",
    "token": "QaSCg8jz",
    "url": "https://divar.ir/v/QaSCg8jz",
    "image": "https://s100.divarcdn.com/static/photo/neda/webp_thumbnail/pDKpo6V-n4bTEEaZ-A2biA/9cd57ac7-ba4b-484e-a9c1-eb0f3128b951.webp"
  },
  {
    "title": "نیسان امیتیس پلاس",
    "subtitle": "۰ کیلومتر",
    "price": "۵,۰۵۰,۰۰۰,۰۰۰ تومان",
    "city": "مشهد",
    "location": "سلام",
    "token": "QadO3tYd",
    "url": "https://divar.ir/v/QadO3tYd",
    "image": "https://s100.divarcdn.com/static/photo/neda/webp_thumbnail/6WEKMugrTTMJlAA_QJAVDg/1abb60f8-d0a4-4db9-b73f-21b43f1c5785.webp"
  },
  {
    "title": "تویوتا کمری هیبریدی ژاپنی صفر",
    "subtitle": "۰ کیلومتر",
    "price": "۱۰,۰۰۰,۰۰۰,۰۰۰ تومان",
    "city": "مشهد",
    "location": "نوفل لوشاتو",
    "token": "Qad-mvn8",
    "url": "https://divar.ir/v/Qad-mvn8",
    "image": "https://s100.divarcdn.com/static/photo/neda/webp_thumbnail/n3636qKtmXtzHn2CG4HQww/812557d4-60c1-49dd-9063-47b451925415.webp"
  },
  {
    "title": "۲۰۷ اتومات پانا",
    "subtitle": "۰ کیلومتر",
    "price": "۱,۸۸۰,۰۰۰,۰۰۰ تومان",
    "city": "مشهد",
    "location": "هنرستان",
    "token": "Qad6G0A_",
    "url": "https://divar.ir/v/Qad6G0A_",
    "image": "https://s100.divarcdn.com/static/photo/neda/webp_thumbnail/Z478I4kKp9pa07-12Cpcfw/a9108a98-036a-43af-82e1-8ff5f10020bf.webp"
  },
  {
    "title": "کوییک gxr L صفر فول آپشن - رینگ اسپرت",
    "subtitle": "۰ کیلومتر",
    "price": "۹۷۰,۰۰۰,۰۰۰ تومان",
    "city": "مشهد",
    "location": "حرم مطهر رضوی",
    "token": "QaUGCvG1",
    "url": "https://divar.ir/v/QaUGCvG1",
    "image": "https://s100.divarcdn.com/static/photo/neda/webp_thumbnail/oxB38FloWrKAS45BmV3aLg/34c22b17-a5dc-41ef-ba5f-55358bcfa581.webp"
  },
  {
    "title": "اشکودا سوپرب 2024 مشکی صفر",
    "subtitle": "۰ کیلومتر",
    "price": "۴,۶۰۰,۰۰۰,۰۰۰ تومان",
    "city": "مشهد",
    "location": "فلسطین",
    "token": "Qad2mLO3",
    "url": "https://divar.ir/v/Qad2mLO3",
    "image": "https://s100.divarcdn.com/static/photo/neda/webp_thumbnail/01ziH_qPXfqVRbCwpCwqJA/370639a9-81b1-4712-888f-e6f005ada974.jpg.webp"
  },
  {
    "title": "حواله نیسان آلتیما قیمت 5/888",
    "subtitle": "۰ کیلومتر",
    "price": "۱۵۰,۰۰۰,۰۰۰ تومان",
    "city": "مشهد",
    "location": "هفت تیر (حافظ)",
    "token": "QadyGwnY",
    "url": "https://divar.ir/v/QadyGwnY",
    "image": "https://s100.divarcdn.com/static/photo/neda/webp_thumbnail/CGo_kFnx3WmTp-EdtZHDvA/73b445bc-fa16-4974-95c2-2660bd0ade29.webp"
  },
  {
    "title": "اتیما ۲۰۲۵ خشک",
    "subtitle": "۰ کیلومتر",
    "price": "۷,۰۰۰,۰۰۰,۰۰۰ تومان",
    "city": "مشهد",
    "location": "حرم مطهر رضوی",
    "token": "QadyGSPG",
    "url": "https://divar.ir/v/QadyGSPG",
    "image": "https://s100.divarcdn.com/static/photo/neda/webp_thumbnail/LxUFTc_vawwk4veEYhAcoA/c3eca785-9743-4ea3-9c7e-0b439c0feba7.webp"
  },
  {
    "title": "شاهین g 1403 صفر",
    "subtitle": "۰ کیلومتر",
    "price": "۱,۶۰۰,۰۰۰,۰۰۰ تومان",
    "city": "مشهد",
    "location": "حسابی جنوبی (شهرک غرب)",
    "token": "QaduGs95",
    "url": "https://divar.ir/v/QaduGs95",
    "image": "https://s100.divarcdn.com/static/photo/neda/webp_thumbnail/m5zupgvyTKMcBXnLyBX8Lg/41ec7066-9150-4cc3-abcf-ac55539d3c56.webp"
  },
  {
    "title": "پژو۲۰۷ صفرTu5p  سقف فلز ۱۴۰۴ سقف فلزمعاوضه هم دارم",
    "subtitle": "۰ کیلومتر",
    "price": "۱,۴۶۰,۰۰۰,۰۰۰ تومان",
    "city": "مشهد",
    "location": "شهید فرامرز عباسی",
    "token": "QacqQSMl",
    "url": "https://divar.ir/v/QacqQSMl",
    "image": "https://s100.divarcdn.com/static/photo/neda/webp_thumbnail/ETjt1ZSVdqTl87QdabAHhg/8b8549e7-70ef-45cb-9d1f-8840dfda07ce.webp"
  },
  {
    "title": "زامیاد اکستند دوگانه",
    "subtitle": "۰ کیلومتر",
    "price": "۱,۲۰۰,۰۰۰,۰۰۰ تومان",
    "city": "مشهد",
    "location": "شهرک لشکر (شهرک غرب)",
    "token": "Qada2BEG",
    "url": "https://divar.ir/v/Qada2BEG",
    "image": "https://s100.divarcdn.com/static/photo/neda/webp_thumbnail/OIGIMdOgw0XR8jdKH7Eg0Q/31cd332d-d702-4a5c-9a12-a0e1d1654651.webp"
  },
  {
    "title": "پارس نوا ال نودجدید",
    "subtitle": "۰ کیلومتر",
    "price": "۲,۴۵۰,۰۰۰,۰۰۰ تومان",
    "city": "مشهد",
    "location": "شریف",
    "token": "QadmmbA_",
    "url": "https://divar.ir/v/QadmmbA_",
    "image": "https://s100.divarcdn.com/static/photo/neda/webp_thumbnail/aS_57NyAcTlkQ-LULir1jA/e1a282b7-6929-4708-998a-ed132133ae25.webp"
  },
  {
    "title": "کوییک s صفر فوری فوری",
    "subtitle": "۰ کیلومتر",
    "price": "۹۰۵,۰۰۰,۰۰۰ تومان",
    "city": "مشهد",
    "location": "سرافرازان",
    "token": "QadaWqnh",
    "url": "https://divar.ir/v/QadaWqnh",
    "image": "https://s100.divarcdn.com/static/photo/neda/webp_thumbnail/h5WONB3W0hx6_U8_rFtzZg/83f0fb59-6bbf-437b-aca3-452943f37ec5.webp"
  },
  {
    "title": "۲۰۷پانا دنده tu5p",
    "subtitle": "۰ کیلومتر",
    "price": "۱,۵۶۰,۰۰۰,۰۰۰ تومان",
    "city": "مشهد",
    "location": "فدک",
    "token": "QaZSVGKX",
    "url": "https://divar.ir/v/QaZSVGKX",
    "image": "https://s100.divarcdn.com/static/photo/neda/webp_thumbnail/_0SBmrXXNFKZHQcXx94NKw/6a3b317f-d1fc-4c99-be92-08c98b18638b.webp"
  },
  {
    "title": "ساینا s صفر کیلومتر",
    "subtitle": "۰ کیلومتر",
    "price": "۹۴۰,۰۰۰,۰۰۰ تومان",
    "city": "مشهد",
    "location": "شهید مطهری",
    "token": "QadOG9aW",
    "url": "https://divar.ir/v/QadOG9aW",
    "image": "https://s100.divarcdn.com/static/photo/neda/webp_thumbnail/Pc8FXzBGdq9zpGWfxg1yiQ/8edea4ee-e587-4a2d-b107-836877aefaf7.webp"
  },
  {
    "title": "فولکس واگن id4 مدل ۲۰۲۵ صفر",
    "subtitle": "۰ کیلومتر",
    "price": "۵,۴۷۰,۰۰۰,۰۰۰ تومان",
    "city": "مشهد",
    "location": "شهید فرامرز عباسی",
    "token": "QaRm-Fmw",
    "url": "https://divar.ir/v/QaRm-Fmw",
    "image": "https://s100.divarcdn.com/static/photo/neda/webp_thumbnail/7nU8-fzqoQ19-_IPAmiLrw/773b495d-97d7-4eb7-9abd-8f77cef590fe.webp"
  },
  {
    "title": "تارا V1 Plus",
    "subtitle": "۰ کیلومتر",
    "price": "۸۰۰,۰۰۰,۰۰۰ تومان",
    "city": "مشهد",
    "location": "دانشجو",
    "token": "QadOmng8",
    "url": "https://divar.ir/v/QadOmng8",
    "image": "https://s100.divarcdn.com/static/photo/neda/webp_thumbnail/olaoaY9pGrUv_ssf6NJS5w/1526bb8f-60d1-4038-aacc-1fe6960927c6.webp"
  },
  {
    "title": "وانت اریسان ۲ مدل ۱۴۰۴",
    "subtitle": "۰ کیلومتر",
    "price": "۱,۰۰۰ تومان",
    "city": "مشهد",
    "location": "اقبال",
    "token": "QadK21rV",
    "url": "https://divar.ir/v/QadK21rV",
    "image": "https://s100.divarcdn.com/static/photo/neda/webp_thumbnail/yIZXdSzwdHfv50m1VliRgw/93f66e14-ab6d-46a7-a650-1aad918e63ae.webp"
  },
  {
    "title": "ساینا مانیتور دار صفر",
    "subtitle": "۰ کیلومتر",
    "price": "۹۵۰,۰۰۰,۰۰۰ تومان",
    "city": "مشهد",
    "location": "ثامن",
    "token": "QaSePXiz",
    "url": "https://divar.ir/v/QaSePXiz",
    "image": "https://s100.divarcdn.com/static/photo/neda/webp_thumbnail/TT9Qjup2o60O1VMJzwkbzg/7405d02d-888c-4511-acf9-75aa72c8529f.webp"
  },
  {
    "title": "سورن پلاس دریچه سیمی صفر",
    "subtitle": "۰ کیلومتر",
    "price": "۱,۳۷۰,۰۰۰,۰۰۰ تومان",
    "city": "مشهد",
    "location": "سید رضی",
    "token": "QadKGkXV",
    "url": "https://divar.ir/v/QadKGkXV",
    "image": "https://s100.divarcdn.com/static/photo/neda/webp_thumbnail/hWmSFM7hakDGBuEJGPrs6Q/074dca9b-2235-4235-8c51-617e525cd958.webp"
  },
  {
    "title": "جک جی 4 صفر j4",
    "subtitle": "۰ کیلومتر",
    "price": "۱,۸۲۰,۰۰۰,۰۰۰ تومان",
    "city": "مشهد",
    "location": "هفت تیر (آب و برق)",
    "token": "QaRe6gZH",
    "url": "https://divar.ir/v/QaRe6gZH",
    "image": "https://s100.divarcdn.com/static/photo/neda/webp_thumbnail/qAwwyHncfRCLq55tOCJM0Q/aaaccd94-1763-40bd-905f-cb0101f3bd71.webp"
  },
  {
    "title": "شاهین صفر اتوماتیک CVT",
    "subtitle": "۰ کیلومتر",
    "price": "۱,۸۰۰,۰۰۰,۰۰۰ تومان",
    "city": "مشهد",
    "location": "عبادی",
    "token": "QadCW4Hz",
    "url": "https://divar.ir/v/QadCW4Hz",
    "image": "https://s100.divarcdn.com/static/photo/neda/webp_thumbnail/_Olp8oH8rzcXu0yqweUM0w/482d59c6-1da0-43f6-835e-239e89112eaa.webp"
  },
  {
    "title": "دنا پلاس اتوماتیک یکماهه تحویل گرفتم",
    "subtitle": "۰ کیلومتر",
    "price": "۱,۹۸۰,۰۰۰,۰۰۰ تومان",
    "city": "مشهد",
    "location": "هفت تیر (آب و برق)",
    "token": "QadCWPT7",
    "url": "https://divar.ir/v/QadCWPT7",
    "image": "https://s100.divarcdn.com/static/photo/neda/webp_thumbnail/6D2mHDcsYWISa1q5ukrr7g/afc7d6bf-785f-433d-955c-978cde965eab.webp"
  },
  {
    "title": "۲۰۷ tu5p   صفر",
    "subtitle": "۰ کیلومتر",
    "price": "۱۵,۳۰۰,۰۰۰ تومان",
    "city": "مشهد",
    "location": "مشکینی (شهرک غرب)",
    "token": "QadW3Jl1",
    "url": "https://divar.ir/v/QadW3Jl1",
    "image": "https://s100.divarcdn.com/static/photo/neda/webp_thumbnail/h4Z8ghFUfmEJSXU3KPSDPA/12805e55-7534-4f99-99c0-22dd12d0923d.webp"
  },
  {
    "title": "حواله",
    "subtitle": "۰ کیلومتر",
    "price": "۸۰۰,۰۰۰,۰۰۰ تومان",
    "city": "مشهد",
    "location": "آزادشهر",
    "token": "QaSCg8jz",
    "url": "https://divar.ir/v/QaSCg8jz",
    "image": "https://s100.divarcdn.com/static/photo/neda/webp_thumbnail/pDKpo6V-n4bTEEaZ-A2biA/9cd57ac7-ba4b-484e-a9c1-eb0f3128b951.webp"
  },
  {
    "title": "نیسان امیتیس پلاس",
    "subtitle": "۰ کیلومتر",
    "price": "۵,۰۵۰,۰۰۰,۰۰۰ تومان",
    "city": "مشهد",
    "location": "سلام",
    "token": "QadO3tYd",
    "url": "https://divar.ir/v/QadO3tYd",
    "image": "https://s100.divarcdn.com/static/photo/neda/webp_thumbnail/6WEKMugrTTMJlAA_QJAVDg/1abb60f8-d0a4-4db9-b73f-21b43f1c5785.webp"
  },
  {
    "title": "تویوتا کمری هیبریدی ژاپنی صفر",
    "subtitle": "۰ کیلومتر",
    "price": "۱۰,۰۰۰,۰۰۰,۰۰۰ تومان",
    "city": "مشهد",
    "location": "نوفل لوشاتو",
    "token": "Qad-mvn8",
    "url": "https://divar.ir/v/Qad-mvn8",
    "image": "https://s100.divarcdn.com/static/photo/neda/webp_thumbnail/n3636qKtmXtzHn2CG4HQww/812557d4-60c1-49dd-9063-47b451925415.webp"
  },
  {
    "title": "۲۰۷ اتومات پانا",
    "subtitle": "۰ کیلومتر",
    "price": "۱,۸۸۰,۰۰۰,۰۰۰ تومان",
    "city": "مشهد",
    "location": "هنرستان",
    "token": "Qad6G0A_",
    "url": "https://divar.ir/v/Qad6G0A_",
    "image": "https://s100.divarcdn.com/static/photo/neda/webp_thumbnail/Z478I4kKp9pa07-12Cpcfw/a9108a98-036a-43af-82e1-8ff5f10020bf.webp"
  },
  {
    "title": "کوییک gxr L صفر فول آپشن - رینگ اسپرت",
    "subtitle": "۰ کیلومتر",
    "price": "۹۷۰,۰۰۰,۰۰۰ تومان",
    "city": "مشهد",
    "location": "حرم مطهر رضوی",
    "token": "QaUGCvG1",
    "url": "https://divar.ir/v/QaUGCvG1",
    "image": "https://s100.divarcdn.com/static/photo/neda/webp_thumbnail/oxB38FloWrKAS45BmV3aLg/34c22b17-a5dc-41ef-ba5f-55358bcfa581.webp"
  },
  {
    "title": "اشکودا سوپرب 2024 مشکی صفر",
    "subtitle": "۰ کیلومتر",
    "price": "۴,۶۰۰,۰۰۰,۰۰۰ تومان",
    "city": "مشهد",
    "location": "فلسطین",
    "token": "Qad2mLO3",
    "url": "https://divar.ir/v/Qad2mLO3",
    "image": "https://s100.divarcdn.com/static/photo/neda/webp_thumbnail/01ziH_qPXfqVRbCwpCwqJA/370639a9-81b1-4712-888f-e6f005ada974.jpg.webp"
  },
  {
    "title": "حواله نیسان آلتیما قیمت 5/888",
    "subtitle": "۰ کیلومتر",
    "price": "۱۵۰,۰۰۰,۰۰۰ تومان",
    "city": "مشهد",
    "location": "هفت تیر (حافظ)",
    "token": "QadyGwnY",
    "url": "https://divar.ir/v/QadyGwnY",
    "image": "https://s100.divarcdn.com/static/photo/neda/webp_thumbnail/CGo_kFnx3WmTp-EdtZHDvA/73b445bc-fa16-4974-95c2-2660bd0ade29.webp"
  },
  {
    "title": "اتیما ۲۰۲۵ خشک",
    "subtitle": "۰ کیلومتر",
    "price": "۷,۰۰۰,۰۰۰,۰۰۰ تومان",
    "city": "مشهد",
    "location": "حرم مطهر رضوی",
    "token": "QadyGSPG",
    "url": "https://divar.ir/v/QadyGSPG",
    "image": "https://s100.divarcdn.com/static/photo/neda/webp_thumbnail/LxUFTc_vawwk4veEYhAcoA/c3eca785-9743-4ea3-9c7e-0b439c0feba7.webp"
  },
  {
    "title": "شاهین g 1403 صفر",
    "subtitle": "۰ کیلومتر",
    "price": "۱,۶۰۰,۰۰۰,۰۰۰ تومان",
    "city": "مشهد",
    "location": "حسابی جنوبی (شهرک غرب)",
    "token": "QaduGs95",
    "url": "https://divar.ir/v/QaduGs95",
    "image": "https://s100.divarcdn.com/static/photo/neda/webp_thumbnail/m5zupgvyTKMcBXnLyBX8Lg/41ec7066-9150-4cc3-abcf-ac55539d3c56.webp"
  },
  {
    "title": "پژو۲۰۷ صفرTu5p  سقف فلز ۱۴۰۴ سقف فلزمعاوضه هم دارم",
    "subtitle": "۰ کیلومتر",
    "price": "۱,۴۶۰,۰۰۰,۰۰۰ تومان",
    "city": "مشهد",
    "location": "شهید فرامرز عباسی",
    "token": "QacqQSMl",
    "url": "https://divar.ir/v/QacqQSMl",
    "image": "https://s100.divarcdn.com/static/photo/neda/webp_thumbnail/ETjt1ZSVdqTl87QdabAHhg/8b8549e7-70ef-45cb-9d1f-8840dfda07ce.webp"
  },
  {
    "title": "زامیاد اکستند دوگانه",
    "subtitle": "۰ کیلومتر",
    "price": "۱,۲۰۰,۰۰۰,۰۰۰ تومان",
    "city": "مشهد",
    "location": "شهرک لشکر (شهرک غرب)",
    "token": "Qada2BEG",
    "url": "https://divar.ir/v/Qada2BEG",
    "image": "https://s100.divarcdn.com/static/photo/neda/webp_thumbnail/OIGIMdOgw0XR8jdKH7Eg0Q/31cd332d-d702-4a5c-9a12-a0e1d1654651.webp"
  },
  {
    "title": "پارس نوا ال نودجدید",
    "subtitle": "۰ کیلومتر",
    "price": "۲,۴۵۰,۰۰۰,۰۰۰ تومان",
    "city": "مشهد",
    "location": "شریف",
    "token": "QadmmbA_",
    "url": "https://divar.ir/v/QadmmbA_",
    "image": "https://s100.divarcdn.com/static/photo/neda/webp_thumbnail/aS_57NyAcTlkQ-LULir1jA/e1a282b7-6929-4708-998a-ed132133ae25.webp"
  },
  {
    "title": "کوییک s صفر فوری فوری",
    "subtitle": "۰ کیلومتر",
    "price": "۹۰۵,۰۰۰,۰۰۰ تومان",
    "city": "مشهد",
    "location": "سرافرازان",
    "token": "QadaWqnh",
    "url": "https://divar.ir/v/QadaWqnh",
    "image": "https://s100.divarcdn.com/static/photo/neda/webp_thumbnail/h5WONB3W0hx6_U8_rFtzZg/83f0fb59-6bbf-437b-aca3-452943f37ec5.webp"
  },
  {
    "title": "۲۰۷پانا دنده tu5p",
    "subtitle": "۰ کیلومتر",
    "price": "۱,۵۶۰,۰۰۰,۰۰۰ تومان",
    "city": "مشهد",
    "location": "فدک",
    "token": "QaZSVGKX",
    "url": "https://divar.ir/v/QaZSVGKX",
    "image": "https://s100.divarcdn.com/static/photo/neda/webp_thumbnail/_0SBmrXXNFKZHQcXx94NKw/6a3b317f-d1fc-4c99-be92-08c98b18638b.webp"
  },
  {
    "title": "ساینا s صفر کیلومتر",
    "subtitle": "۰ کیلومتر",
    "price": "۹۴۰,۰۰۰,۰۰۰ تومان",
    "city": "مشهد",
    "location": "شهید مطهری",
    "token": "QadOG9aW",
    "url": "https://divar.ir/v/QadOG9aW",
    "image": "https://s100.divarcdn.com/static/photo/neda/webp_thumbnail/Pc8FXzBGdq9zpGWfxg1yiQ/8edea4ee-e587-4a2d-b107-836877aefaf7.webp"
  },
  {
    "title": "فولکس واگن id4 مدل ۲۰۲۵ صفر",
    "subtitle": "۰ کیلومتر",
    "price": "۵,۴۷۰,۰۰۰,۰۰۰ تومان",
    "city": "مشهد",
    "location": "شهید فرامرز عباسی",
    "token": "QaRm-Fmw",
    "url": "https://divar.ir/v/QaRm-Fmw",
    "image": "https://s100.divarcdn.com/static/photo/neda/webp_thumbnail/7nU8-fzqoQ19-_IPAmiLrw/773b495d-97d7-4eb7-9abd-8f77cef590fe.webp"
  },
  {
    "title": "تارا V1 Plus",
    "subtitle": "۰ کیلومتر",
    "price": "۸۰۰,۰۰۰,۰۰۰ تومان",
    "city": "مشهد",
    "location": "دانشجو",
    "token": "QadOmng8",
    "url": "https://divar.ir/v/QadOmng8",
    "image": "https://s100.divarcdn.com/static/photo/neda/webp_thumbnail/olaoaY9pGrUv_ssf6NJS5w/1526bb8f-60d1-4038-aacc-1fe6960927c6.webp"
  },
  {
    "title": "وانت اریسان ۲ مدل ۱۴۰۴",
    "subtitle": "۰ کیلومتر",
    "price": "۱,۰۰۰ تومان",
    "city": "مشهد",
    "location": "اقبال",
    "token": "QadK21rV",
    "url": "https://divar.ir/v/QadK21rV",
    "image": "https://s100.divarcdn.com/static/photo/neda/webp_thumbnail/yIZXdSzwdHfv50m1VliRgw/93f66e14-ab6d-46a7-a650-1aad918e63ae.webp"
  },
  {
    "title": "ساینا مانیتور دار صفر",
    "subtitle": "۰ کیلومتر",
    "price": "۹۵۰,۰۰۰,۰۰۰ تومان",
    "city": "مشهد",
    "location": "ثامن",
    "token": "QaSePXiz",
    "url": "https://divar.ir/v/QaSePXiz",
    "image": "https://s100.divarcdn.com/static/photo/neda/webp_thumbnail/TT9Qjup2o60O1VMJzwkbzg/7405d02d-888c-4511-acf9-75aa72c8529f.webp"
  },
  {
    "title": "سورن پلاس دریچه سیمی صفر",
    "subtitle": "۰ کیلومتر",
    "price": "۱,۳۷۰,۰۰۰,۰۰۰ تومان",
    "city": "مشهد",
    "location": "سید رضی",
    "token": "QadKGkXV",
    "url": "https://divar.ir/v/QadKGkXV",
    "image": "https://s100.divarcdn.com/static/photo/neda/webp_thumbnail/hWmSFM7hakDGBuEJGPrs6Q/074dca9b-2235-4235-8c51-617e525cd958.webp"
  },
  {
    "title": "جک جی 4 صفر j4",
    "subtitle": "۰ کیلومتر",
    "price": "۱,۸۲۰,۰۰۰,۰۰۰ تومان",
    "city": "مشهد",
    "location": "هفت تیر (آب و برق)",
    "token": "QaRe6gZH",
    "url": "https://divar.ir/v/QaRe6gZH",
    "image": "https://s100.divarcdn.com/static/photo/neda/webp_thumbnail/qAwwyHncfRCLq55tOCJM0Q/aaaccd94-1763-40bd-905f-cb0101f3bd71.webp"
  },
  {
    "title": "شاهین صفر اتوماتیک CVT",
    "subtitle": "۰ کیلومتر",
    "price": "۱,۸۰۰,۰۰۰,۰۰۰ تومان",
    "city": "مشهد",
    "location": "عبادی",
    "token": "QadCW4Hz",
    "url": "https://divar.ir/v/QadCW4Hz",
    "image": "https://s100.divarcdn.com/static/photo/neda/webp_thumbnail/_Olp8oH8rzcXu0yqweUM0w/482d59c6-1da0-43f6-835e-239e89112eaa.webp"
  },
  {
    "title": "دنا پلاس اتوماتیک یکماهه تحویل گرفتم",
    "subtitle": "۰ کیلومتر",
    "price": "۱,۹۸۰,۰۰۰,۰۰۰ تومان",
    "city": "مشهد",
    "location": "هفت تیر (آب و برق)",
    "token": "QadCWPT7",
    "url": "https://divar.ir/v/QadCWPT7",
    "image": "https://s100.divarcdn.com/static/photo/neda/webp_thumbnail/6D2mHDcsYWISa1q5ukrr7g/afc7d6bf-785f-433d-955c-978cde965eab.webp"
  },
  {
    "title": "۲۰۷ tu5p   صفر",
    "subtitle": "۰ کیلومتر",
    "price": "۱۵,۳۰۰,۰۰۰ تومان",
    "city": "مشهد",
    "location": "مشکینی (شهرک غرب)",
    "token": "QadW3Jl1",
    "url": "https://divar.ir/v/QadW3Jl1",
    "image": "https://s100.divarcdn.com/static/photo/neda/webp_thumbnail/h4Z8ghFUfmEJSXU3KPSDPA/12805e55-7534-4f99-99c0-22dd12d0923d.webp"
  },
  {
    "title": "حواله",
    "subtitle": "۰ کیلومتر",
    "price": "۸۰۰,۰۰۰,۰۰۰ تومان",
    "city": "مشهد",
    "location": "آزادشهر",
    "token": "QaSCg8jz",
    "url": "https://divar.ir/v/QaSCg8jz",
    "image": "https://s100.divarcdn.com/static/photo/neda/webp_thumbnail/pDKpo6V-n4bTEEaZ-A2biA/9cd57ac7-ba4b-484e-a9c1-eb0f3128b951.webp"
  },
  {
    "title": "نیسان امیتیس پلاس",
    "subtitle": "۰ کیلومتر",
    "price": "۵,۰۵۰,۰۰۰,۰۰۰ تومان",
    "city": "مشهد",
    "location": "سلام",
    "token": "QadO3tYd",
    "url": "https://divar.ir/v/QadO3tYd",
    "image": "https://s100.divarcdn.com/static/photo/neda/webp_thumbnail/6WEKMugrTTMJlAA_QJAVDg/1abb60f8-d0a4-4db9-b73f-21b43f1c5785.webp"
  },
  {
    "title": "تویوتا کمری هیبریدی ژاپنی صفر",
    "subtitle": "۰ کیلومتر",
    "price": "۱۰,۰۰۰,۰۰۰,۰۰۰ تومان",
    "city": "مشهد",
    "location": "نوفل لوشاتو",
    "token": "Qad-mvn8",
    "url": "https://divar.ir/v/Qad-mvn8",
    "image": "https://s100.divarcdn.com/static/photo/neda/webp_thumbnail/n3636qKtmXtzHn2CG4HQww/812557d4-60c1-49dd-9063-47b451925415.webp"
  },
  {
    "title": "۲۰۷ اتومات پانا",
    "subtitle": "۰ کیلومتر",
    "price": "۱,۸۸۰,۰۰۰,۰۰۰ تومان",
    "city": "مشهد",
    "location": "هنرستان",
    "token": "Qad6G0A_",
    "url": "https://divar.ir/v/Qad6G0A_",
    "image": "https://s100.divarcdn.com/static/photo/neda/webp_thumbnail/Z478I4kKp9pa07-12Cpcfw/a9108a98-036a-43af-82e1-8ff5f10020bf.webp"
  },
  {
    "title": "کوییک gxr L صفر فول آپشن - رینگ اسپرت",
    "subtitle": "۰ کیلومتر",
    "price": "۹۷۰,۰۰۰,۰۰۰ تومان",
    "city": "مشهد",
    "location": "حرم مطهر رضوی",
    "token": "QaUGCvG1",
    "url": "https://divar.ir/v/QaUGCvG1",
    "image": "https://s100.divarcdn.com/static/photo/neda/webp_thumbnail/oxB38FloWrKAS45BmV3aLg/34c22b17-a5dc-41ef-ba5f-55358bcfa581.webp"
  },
  {
    "title": "اشکودا سوپرب 2024 مشکی صفر",
    "subtitle": "۰ کیلومتر",
    "price": "۴,۶۰۰,۰۰۰,۰۰۰ تومان",
    "city": "مشهد",
    "location": "فلسطین",
    "token": "Qad2mLO3",
    "url": "https://divar.ir/v/Qad2mLO3",
    "image": "https://s100.divarcdn.com/static/photo/neda/webp_thumbnail/01ziH_qPXfqVRbCwpCwqJA/370639a9-81b1-4712-888f-e6f005ada974.jpg.webp"
  },
  {
    "title": "حواله نیسان آلتیما قیمت 5/888",
    "subtitle": "۰ کیلومتر",
    "price": "۱۵۰,۰۰۰,۰۰۰ تومان",
    "city": "مشهد",
    "location": "هفت تیر (حافظ)",
    "token": "QadyGwnY",
    "url": "https://divar.ir/v/QadyGwnY",
    "image": "https://s100.divarcdn.com/static/photo/neda/webp_thumbnail/CGo_kFnx3WmTp-EdtZHDvA/73b445bc-fa16-4974-95c2-2660bd0ade29.webp"
  },
  {
    "title": "اتیما ۲۰۲۵ خشک",
    "subtitle": "۰ کیلومتر",
    "price": "۷,۰۰۰,۰۰۰,۰۰۰ تومان",
    "city": "مشهد",
    "location": "حرم مطهر رضوی",
    "token": "QadyGSPG",
    "url": "https://divar.ir/v/QadyGSPG",
    "image": "https://s100.divarcdn.com/static/photo/neda/webp_thumbnail/LxUFTc_vawwk4veEYhAcoA/c3eca785-9743-4ea3-9c7e-0b439c0feba7.webp"
  },
  {
    "title": "شاهین g 1403 صفر",
    "subtitle": "۰ کیلومتر",
    "price": "۱,۶۰۰,۰۰۰,۰۰۰ تومان",
    "city": "مشهد",
    "location": "حسابی جنوبی (شهرک غرب)",
    "token": "QaduGs95",
    "url": "https://divar.ir/v/QaduGs95",
    "image": "https://s100.divarcdn.com/static/photo/neda/webp_thumbnail/m5zupgvyTKMcBXnLyBX8Lg/41ec7066-9150-4cc3-abcf-ac55539d3c56.webp"
  },
  {
    "title": "پژو۲۰۷ صفرTu5p  سقف فلز ۱۴۰۴ سقف فلزمعاوضه هم دارم",
    "subtitle": "۰ کیلومتر",
    "price": "۱,۴۶۰,۰۰۰,۰۰۰ تومان",
    "city": "مشهد",
    "location": "شهید فرامرز عباسی",
    "token": "QacqQSMl",
    "url": "https://divar.ir/v/QacqQSMl",
    "image": "https://s100.divarcdn.com/static/photo/neda/webp_thumbnail/ETjt1ZSVdqTl87QdabAHhg/8b8549e7-70ef-45cb-9d1f-8840dfda07ce.webp"
  },
  {
    "title": "زامیاد اکستند دوگانه",
    "subtitle": "۰ کیلومتر",
    "price": "۱,۲۰۰,۰۰۰,۰۰۰ تومان",
    "city": "مشهد",
    "location": "شهرک لشکر (شهرک غرب)",
    "token": "Qada2BEG",
    "url": "https://divar.ir/v/Qada2BEG",
    "image": "https://s100.divarcdn.com/static/photo/neda/webp_thumbnail/OIGIMdOgw0XR8jdKH7Eg0Q/31cd332d-d702-4a5c-9a12-a0e1d1654651.webp"
  },
  {
    "title": "پارس نوا ال نودجدید",
    "subtitle": "۰ کیلومتر",
    "price": "۲,۴۵۰,۰۰۰,۰۰۰ تومان",
    "city": "مشهد",
    "location": "شریف",
    "token": "QadmmbA_",
    "url": "https://divar.ir/v/QadmmbA_",
    "image": "https://s100.divarcdn.com/static/photo/neda/webp_thumbnail/aS_57NyAcTlkQ-LULir1jA/e1a282b7-6929-4708-998a-ed132133ae25.webp"
  },
  {
    "title": "کوییک s صفر فوری فوری",
    "subtitle": "۰ کیلومتر",
    "price": "۹۰۵,۰۰۰,۰۰۰ تومان",
    "city": "مشهد",
    "location": "سرافرازان",
    "token": "QadaWqnh",
    "url": "https://divar.ir/v/QadaWqnh",
    "image": "https://s100.divarcdn.com/static/photo/neda/webp_thumbnail/h5WONB3W0hx6_U8_rFtzZg/83f0fb59-6bbf-437b-aca3-452943f37ec5.webp"
  },
  {
    "title": "۲۰۷پانا دنده tu5p",
    "subtitle": "۰ کیلومتر",
    "price": "۱,۵۶۰,۰۰۰,۰۰۰ تومان",
    "city": "مشهد",
    "location": "فدک",
    "token": "QaZSVGKX",
    "url": "https://divar.ir/v/QaZSVGKX",
    "image": "https://s100.divarcdn.com/static/photo/neda/webp_thumbnail/_0SBmrXXNFKZHQcXx94NKw/6a3b317f-d1fc-4c99-be92-08c98b18638b.webp"
  },
  {
    "title": "ساینا s صفر کیلومتر",
    "subtitle": "۰ کیلومتر",
    "price": "۹۴۰,۰۰۰,۰۰۰ تومان",
    "city": "مشهد",
    "location": "شهید مطهری",
    "token": "QadOG9aW",
    "url": "https://divar.ir/v/QadOG9aW",
    "image": "https://s100.divarcdn.com/static/photo/neda/webp_thumbnail/Pc8FXzBGdq9zpGWfxg1yiQ/8edea4ee-e587-4a2d-b107-836877aefaf7.webp"
  },
  {
    "title": "فولکس واگن id4 مدل ۲۰۲۵ صفر",
    "subtitle": "۰ کیلومتر",
    "price": "۵,۴۷۰,۰۰۰,۰۰۰ تومان",
    "city": "مشهد",
    "location": "شهید فرامرز عباسی",
    "token": "QaRm-Fmw",
    "url": "https://divar.ir/v/QaRm-Fmw",
    "image": "https://s100.divarcdn.com/static/photo/neda/webp_thumbnail/7nU8-fzqoQ19-_IPAmiLrw/773b495d-97d7-4eb7-9abd-8f77cef590fe.webp"
  },
  {
    "title": "تارا V1 Plus",
    "subtitle": "۰ کیلومتر",
    "price": "۸۰۰,۰۰۰,۰۰۰ تومان",
    "city": "مشهد",
    "location": "دانشجو",
    "token": "QadOmng8",
    "url": "https://divar.ir/v/QadOmng8",
    "image": "https://s100.divarcdn.com/static/photo/neda/webp_thumbnail/olaoaY9pGrUv_ssf6NJS5w/1526bb8f-60d1-4038-aacc-1fe6960927c6.webp"
  },
  {
    "title": "وانت اریسان ۲ مدل ۱۴۰۴",
    "subtitle": "۰ کیلومتر",
    "price": "۱,۰۰۰ تومان",
    "city": "مشهد",
    "location": "اقبال",
    "token": "QadK21rV",
    "url": "https://divar.ir/v/QadK21rV",
    "image": "https://s100.divarcdn.com/static/photo/neda/webp_thumbnail/yIZXdSzwdHfv50m1VliRgw/93f66e14-ab6d-46a7-a650-1aad918e63ae.webp"
  },
  {
    "title": "ساینا مانیتور دار صفر",
    "subtitle": "۰ کیلومتر",
    "price": "۹۵۰,۰۰۰,۰۰۰ تومان",
    "city": "مشهد",
    "location": "ثامن",
    "token": "QaSePXiz",
    "url": "https://divar.ir/v/QaSePXiz",
    "image": "https://s100.divarcdn.com/static/photo/neda/webp_thumbnail/TT9Qjup2o60O1VMJzwkbzg/7405d02d-888c-4511-acf9-75aa72c8529f.webp"
  },
  {
    "title": "سورن پلاس دریچه سیمی صفر",
    "subtitle": "۰ کیلومتر",
    "price": "۱,۳۷۰,۰۰۰,۰۰۰ تومان",
    "city": "مشهد",
    "location": "سید رضی",
    "token": "QadKGkXV",
    "url": "https://divar.ir/v/QadKGkXV",
    "image": "https://s100.divarcdn.com/static/photo/neda/webp_thumbnail/hWmSFM7hakDGBuEJGPrs6Q/074dca9b-2235-4235-8c51-617e525cd958.webp"
  },
  {
    "title": "جک جی 4 صفر j4",
    "subtitle": "۰ کیلومتر",
    "price": "۱,۸۲۰,۰۰۰,۰۰۰ تومان",
    "city": "مشهد",
    "location": "هفت تیر (آب و برق)",
    "token": "QaRe6gZH",
    "url": "https://divar.ir/v/QaRe6gZH",
    "image": "https://s100.divarcdn.com/static/photo/neda/webp_thumbnail/qAwwyHncfRCLq55tOCJM0Q/aaaccd94-1763-40bd-905f-cb0101f3bd71.webp"
  },
  {
    "title": "شاهین صفر اتوماتیک CVT",
    "subtitle": "۰ کیلومتر",
    "price": "۱,۸۰۰,۰۰۰,۰۰۰ تومان",
    "city": "مشهد",
    "location": "عبادی",
    "token": "QadCW4Hz",
    "url": "https://divar.ir/v/QadCW4Hz",
    "image": "https://s100.divarcdn.com/static/photo/neda/webp_thumbnail/_Olp8oH8rzcXu0yqweUM0w/482d59c6-1da0-43f6-835e-239e89112eaa.webp"
  },
  {
    "title": "دنا پلاس اتوماتیک یکماهه تحویل گرفتم",
    "subtitle": "۰ کیلومتر",
    "price": "۱,۹۸۰,۰۰۰,۰۰۰ تومان",
    "city": "مشهد",
    "location": "هفت تیر (آب و برق)",
    "token": "QadCWPT7",
    "url": "https://divar.ir/v/QadCWPT7",
    "image": "https://s100.divarcdn.com/static/photo/neda/webp_thumbnail/6D2mHDcsYWISa1q5ukrr7g/afc7d6bf-785f-433d-955c-978cde965eab.webp"
  },
  {
    "title": "۲۰۷ tu5p   صفر",
    "subtitle": "۰ کیلومتر",
    "price": "۱۵,۳۰۰,۰۰۰ تومان",
    "city": "مشهد",
    "location": "مشکینی (شهرک غرب)",
    "token": "QadW3Jl1",
    "url": "https://divar.ir/v/QadW3Jl1",
    "image": "https://s100.divarcdn.com/static/photo/neda/webp_thumbnail/h4Z8ghFUfmEJSXU3KPSDPA/12805e55-7534-4f99-99c0-22dd12d0923d.webp"
  },
  {
    "title": "حواله",
    "subtitle": "۰ کیلومتر",
    "price": "۸۰۰,۰۰۰,۰۰۰ تومان",
    "city": "مشهد",
    "location": "آزادشهر",
    "token": "QaSCg8jz",
    "url": "https://divar.ir/v/QaSCg8jz",
    "image": "https://s100.divarcdn.com/static/photo/neda/webp_thumbnail/pDKpo6V-n4bTEEaZ-A2biA/9cd57ac7-ba4b-484e-a9c1-eb0f3128b951.webp"
  },
  {
    "title": "نیسان امیتیس پلاس",
    "subtitle": "۰ کیلومتر",
    "price": "۵,۰۵۰,۰۰۰,۰۰۰ تومان",
    "city": "مشهد",
    "location": "سلام",
    "token": "QadO3tYd",
    "url": "https://divar.ir/v/QadO3tYd",
    "image": "https://s100.divarcdn.com/static/photo/neda/webp_thumbnail/6WEKMugrTTMJlAA_QJAVDg/1abb60f8-d0a4-4db9-b73f-21b43f1c5785.webp"
  },
  {
    "title": "تویوتا کمری هیبریدی ژاپنی صفر",
    "subtitle": "۰ کیلومتر",
    "price": "۱۰,۰۰۰,۰۰۰,۰۰۰ تومان",
    "city": "مشهد",
    "location": "نوفل لوشاتو",
    "token": "Qad-mvn8",
    "url": "https://divar.ir/v/Qad-mvn8",
    "image": "https://s100.divarcdn.com/static/photo/neda/webp_thumbnail/n3636qKtmXtzHn2CG4HQww/812557d4-60c1-49dd-9063-47b451925415.webp"
  },
  {
    "title": "۲۰۷ اتومات پانا",
    "subtitle": "۰ کیلومتر",
    "price": "۱,۸۸۰,۰۰۰,۰۰۰ تومان",
    "city": "مشهد",
    "location": "هنرستان",
    "token": "Qad6G0A_",
    "url": "https://divar.ir/v/Qad6G0A_",
    "image": "https://s100.divarcdn.com/static/photo/neda/webp_thumbnail/Z478I4kKp9pa07-12Cpcfw/a9108a98-036a-43af-82e1-8ff5f10020bf.webp"
  },
  {
    "title": "کوییک gxr L صفر فول آپشن - رینگ اسپرت",
    "subtitle": "۰ کیلومتر",
    "price": "۹۷۰,۰۰۰,۰۰۰ تومان",
    "city": "مشهد",
    "location": "حرم مطهر رضوی",
    "token": "QaUGCvG1",
    "url": "https://divar.ir/v/QaUGCvG1",
    "image": "https://s100.divarcdn.com/static/photo/neda/webp_thumbnail/oxB38FloWrKAS45BmV3aLg/34c22b17-a5dc-41ef-ba5f-55358bcfa581.webp"
  },
  {
    "title": "اشکودا سوپرب 2024 مشکی صفر",
    "subtitle": "۰ کیلومتر",
    "price": "۴,۶۰۰,۰۰۰,۰۰۰ تومان",
    "city": "مشهد",
    "location": "فلسطین",
    "token": "Qad2mLO3",
    "url": "https://divar.ir/v/Qad2mLO3",
    "image": "https://s100.divarcdn.com/static/photo/neda/webp_thumbnail/01ziH_qPXfqVRbCwpCwqJA/370639a9-81b1-4712-888f-e6f005ada974.jpg.webp"
  },
  {
    "title": "حواله نیسان آلتیما قیمت 5/888",
    "subtitle": "۰ کیلومتر",
    "price": "۱۵۰,۰۰۰,۰۰۰ تومان",
    "city": "مشهد",
    "location": "هفت تیر (حافظ)",
    "token": "QadyGwnY",
    "url": "https://divar.ir/v/QadyGwnY",
    "image": "https://s100.divarcdn.com/static/photo/neda/webp_thumbnail/CGo_kFnx3WmTp-EdtZHDvA/73b445bc-fa16-4974-95c2-2660bd0ade29.webp"
  },
  {
    "title": "اتیما ۲۰۲۵ خشک",
    "subtitle": "۰ کیلومتر",
    "price": "۷,۰۰۰,۰۰۰,۰۰۰ تومان",
    "city": "مشهد",
    "location": "حرم مطهر رضوی",
    "token": "QadyGSPG",
    "url": "https://divar.ir/v/QadyGSPG",
    "image": "https://s100.divarcdn.com/static/photo/neda/webp_thumbnail/LxUFTc_vawwk4veEYhAcoA/c3eca785-9743-4ea3-9c7e-0b439c0feba7.webp"
  },
  {
    "title": "شاهین g 1403 صفر",
    "subtitle": "۰ کیلومتر",
    "price": "۱,۶۰۰,۰۰۰,۰۰۰ تومان",
    "city": "مشهد",
    "location": "حسابی جنوبی (شهرک غرب)",
    "token": "QaduGs95",
    "url": "https://divar.ir/v/QaduGs95",
    "image": "https://s100.divarcdn.com/static/photo/neda/webp_thumbnail/m5zupgvyTKMcBXnLyBX8Lg/41ec7066-9150-4cc3-abcf-ac55539d3c56.webp"
  },
  {
    "title": "پژو۲۰۷ صفرTu5p  سقف فلز ۱۴۰۴ سقف فلزمعاوضه هم دارم",
    "subtitle": "۰ کیلومتر",
    "price": "۱,۴۶۰,۰۰۰,۰۰۰ تومان",
    "city": "مشهد",
    "location": "شهید فرامرز عباسی",
    "token": "QacqQSMl",
    "url": "https://divar.ir/v/QacqQSMl",
    "image": "https://s100.divarcdn.com/static/photo/neda/webp_thumbnail/ETjt1ZSVdqTl87QdabAHhg/8b8549e7-70ef-45cb-9d1f-8840dfda07ce.webp"
  },
  {
    "title": "زامیاد اکستند دوگانه",
    "subtitle": "۰ کیلومتر",
    "price": "۱,۲۰۰,۰۰۰,۰۰۰ تومان",
    "city": "مشهد",
    "location": "شهرک لشکر (شهرک غرب)",
    "token": "Qada2BEG",
    "url": "https://divar.ir/v/Qada2BEG",
    "image": "https://s100.divarcdn.com/static/photo/neda/webp_thumbnail/OIGIMdOgw0XR8jdKH7Eg0Q/31cd332d-d702-4a5c-9a12-a0e1d1654651.webp"
  },
  {
    "title": "پارس نوا ال نودجدید",
    "subtitle": "۰ کیلومتر",
    "price": "۲,۴۵۰,۰۰۰,۰۰۰ تومان",
    "city": "مشهد",
    "location": "شریف",
    "token": "QadmmbA_",
    "url": "https://divar.ir/v/QadmmbA_",
    "image": "https://s100.divarcdn.com/static/photo/neda/webp_thumbnail/aS_57NyAcTlkQ-LULir1jA/e1a282b7-6929-4708-998a-ed132133ae25.webp"
  },
  {
    "title": "کوییک s صفر فوری فوری",
    "subtitle": "۰ کیلومتر",
    "price": "۹۰۵,۰۰۰,۰۰۰ تومان",
    "city": "مشهد",
    "location": "سرافرازان",
    "token": "QadaWqnh",
    "url": "https://divar.ir/v/QadaWqnh",
    "image": "https://s100.divarcdn.com/static/photo/neda/webp_thumbnail/h5WONB3W0hx6_U8_rFtzZg/83f0fb59-6bbf-437b-aca3-452943f37ec5.webp"
  },
  {
    "title": "۲۰۷پانا دنده tu5p",
    "subtitle": "۰ کیلومتر",
    "price": "۱,۵۶۰,۰۰۰,۰۰۰ تومان",
    "city": "مشهد",
    "location": "فدک",
    "token": "QaZSVGKX",
    "url": "https://divar.ir/v/QaZSVGKX",
    "image": "https://s100.divarcdn.com/static/photo/neda/webp_thumbnail/_0SBmrXXNFKZHQcXx94NKw/6a3b317f-d1fc-4c99-be92-08c98b18638b.webp"
  },
  {
    "title": "ساینا s صفر کیلومتر",
    "subtitle": "۰ کیلومتر",
    "price": "۹۴۰,۰۰۰,۰۰۰ تومان",
    "city": "مشهد",
    "location": "شهید مطهری",
    "token": "QadOG9aW",
    "url": "https://divar.ir/v/QadOG9aW",
    "image": "https://s100.divarcdn.com/static/photo/neda/webp_thumbnail/Pc8FXzBGdq9zpGWfxg1yiQ/8edea4ee-e587-4a2d-b107-836877aefaf7.webp"
  },
  {
    "title": "فولکس واگن id4 مدل ۲۰۲۵ صفر",
    "subtitle": "۰ کیلومتر",
    "price": "۵,۴۷۰,۰۰۰,۰۰۰ تومان",
    "city": "مشهد",
    "location": "شهید فرامرز عباسی",
    "token": "QaRm-Fmw",
    "url": "https://divar.ir/v/QaRm-Fmw",
    "image": "https://s100.divarcdn.com/static/photo/neda/webp_thumbnail/7nU8-fzqoQ19-_IPAmiLrw/773b495d-97d7-4eb7-9abd-8f77cef590fe.webp"
  },
  {
    "title": "تارا V1 Plus",
    "subtitle": "۰ کیلومتر",
    "price": "۸۰۰,۰۰۰,۰۰۰ تومان",
    "city": "مشهد",
    "location": "دانشجو",
    "token": "QadOmng8",
    "url": "https://divar.ir/v/QadOmng8",
    "image": "https://s100.divarcdn.com/static/photo/neda/webp_thumbnail/olaoaY9pGrUv_ssf6NJS5w/1526bb8f-60d1-4038-aacc-1fe6960927c6.webp"
  },
  {
    "title": "وانت اریسان ۲ مدل ۱۴۰۴",
    "subtitle": "۰ کیلومتر",
    "price": "۱,۰۰۰ تومان",
    "city": "مشهد",
    "location": "اقبال",
    "token": "QadK21rV",
    "url": "https://divar.ir/v/QadK21rV",
    "image": "https://s100.divarcdn.com/static/photo/neda/webp_thumbnail/yIZXdSzwdHfv50m1VliRgw/93f66e14-ab6d-46a7-a650-1aad918e63ae.webp"
  },
  {
    "title": "ساینا مانیتور دار صفر",
    "subtitle": "۰ کیلومتر",
    "price": "۹۵۰,۰۰۰,۰۰۰ تومان",
    "city": "مشهد",
    "location": "ثامن",
    "token": "QaSePXiz",
    "url": "https://divar.ir/v/QaSePXiz",
    "image": "https://s100.divarcdn.com/static/photo/neda/webp_thumbnail/TT9Qjup2o60O1VMJzwkbzg/7405d02d-888c-4511-acf9-75aa72c8529f.webp"
  },
  {
    "title": "سورن پلاس دریچه سیمی صفر",
    "subtitle": "۰ کیلومتر",
    "price": "۱,۳۷۰,۰۰۰,۰۰۰ تومان",
    "city": "مشهد",
    "location": "سید رضی",
    "token": "QadKGkXV",
    "url": "https://divar.ir/v/QadKGkXV",
    "image": "https://s100.divarcdn.com/static/photo/neda/webp_thumbnail/hWmSFM7hakDGBuEJGPrs6Q/074dca9b-2235-4235-8c51-617e525cd958.webp"
  },
  {
    "title": "جک جی 4 صفر j4",
    "subtitle": "۰ کیلومتر",
    "price": "۱,۸۲۰,۰۰۰,۰۰۰ تومان",
    "city": "مشهد",
    "location": "هفت تیر (آب و برق)",
    "token": "QaRe6gZH",
    "url": "https://divar.ir/v/QaRe6gZH",
    "image": "https://s100.divarcdn.com/static/photo/neda/webp_thumbnail/qAwwyHncfRCLq55tOCJM0Q/aaaccd94-1763-40bd-905f-cb0101f3bd71.webp"
  },
  {
    "title": "شاهین صفر اتوماتیک CVT",
    "subtitle": "۰ کیلومتر",
    "price": "۱,۸۰۰,۰۰۰,۰۰۰ تومان",
    "city": "مشهد",
    "location": "عبادی",
    "token": "QadCW4Hz",
    "url": "https://divar.ir/v/QadCW4Hz",
    "image": "https://s100.divarcdn.com/static/photo/neda/webp_thumbnail/_Olp8oH8rzcXu0yqweUM0w/482d59c6-1da0-43f6-835e-239e89112eaa.webp"
  },
  {
    "title": "دنا پلاس اتوماتیک یکماهه تحویل گرفتم",
    "subtitle": "۰ کیلومتر",
    "price": "۱,۹۸۰,۰۰۰,۰۰۰ تومان",
    "city": "مشهد",
    "location": "هفت تیر (آب و برق)",
    "token": "QadCWPT7",
    "url": "https://divar.ir/v/QadCWPT7",
    "image": "https://s100.divarcdn.com/static/photo/neda/webp_thumbnail/6D2mHDcsYWISa1q5ukrr7g/afc7d6bf-785f-433d-955c-978cde965eab.webp"
  },
  {
    "title": "نیسان قشقایی 2025 موتور (2 لیتری )",
    "subtitle": "۰ کیلومتر",
    "price": "۵,۵۹۵,۰۰۰,۰۰۰ تومان",
    "city": "تهران",
    "location": "جماران (نیاوران)",
    "token": "QaZmHukQ",
    "url": "https://divar.ir/v/QaZmHukQ",
    "image": "https://s100.divarcdn.com/static/photo/neda/webp_thumbnail/cn285610iH_Ih-ZZrTP95Q/f5af513e-3d0d-4010-90fa-2e567fe623c1.webp"
  },
  {
    "title": "کی‌ام‌سی ایگل /kmc eagle، مدل1404",
    "subtitle": "۰ کیلومتر",
    "price": "۱,۸۰۰,۰۰۰,۰۰۰ تومان",
    "city": "تهران",
    "location": "سهروردی",
    "token": "Qa05mkEX",
    "url": "https://divar.ir/v/Qa05mkEX",
    "image": "https://s100.divarcdn.com/static/photo/neda/webp_thumbnail/yULUcZhfGZ-2EyyRxEmU7Q/c07d4080-6f2b-4876-ba8a-e93f7a59b651.webp"
  },
  {
    "title": "هایما x7اقساط بانکی/تحویل لحظه/اقساط۵ساله",
    "subtitle": "۰ کیلومتر",
    "price": "۱,۳۷۰,۰۰۰,۰۰۰,۰۰۰ تومان",
    "city": "تهران",
    "location": "جنت‌آباد جنوبی",
    "token": "QaUODhgT",
    "url": "https://divar.ir/v/QaUODhgT",
    "image": "https://s100.divarcdn.com/static/photo/neda/webp_thumbnail/L_diKHzMWtoFeXLZDGTXkw/0af2a432-57a6-40c3-b346-f86679ada948.webp"
  },
  {
    "title": "ریرا ایران خودرو ری‌ را توربو/1404و1405تحویل فوری",
    "subtitle": "۰ کیلومتر",
    "price": "۲,۳۶۵,۰۰۰,۰۰۰ تومان",
    "city": "تهران",
    "location": "شهرآرا",
    "token": "QaRi3B2p",
    "url": "https://divar.ir/v/QaRi3B2p",
    "image": "https://s100.divarcdn.com/static/photo/neda/webp_thumbnail/29QAJL6d4pe624VA9bUfkg/abe33801-c3a1-459a-8144-3f0819779aa2.webp"
  },
  {
    "title": "دیگنیتی پرایم Prime داخل مشکی*مارون/*1404صفر روز",
    "subtitle": "۰ کیلومتر",
    "price": "۳,۴۲۵,۰۰۰,۰۰۰ تومان",
    "city": "تهران",
    "location": "شهرآرا",
    "token": "QaVu5g51",
    "url": "https://divar.ir/v/QaVu5g51",
    "image": "https://s100.divarcdn.com/static/photo/neda/webp_thumbnail/iZakerAJsEeHLbw38_aaQg/7455f185-8d83-46c5-8e54-19c8d0bad57c.webp"
  },
  {
    "title": "207 پانوراما اتومات سقف شیشه ای TU5P صفر 1404",
    "subtitle": "۰ کیلومتر",
    "price": "۱,۷۷۰,۰۰۰,۰۰۰ تومان",
    "city": "تهران",
    "location": "فردوس",
    "token": "QasN6Vt0",
    "url": "https://divar.ir/v/QasN6Vt0",
    "image": "https://s100.divarcdn.com/static/photo/neda/webp_thumbnail/3q4HydGhJXu28lR9aaWujA/a1544b86-86e1-4cc4-9ee9-6d40b481f93f.webp"
  },
  {
    "title": "تویوتا لوین بنزینی ۱۲۰۰ توربو ۲۰۲۴ صفر خشک",
    "subtitle": "۰ کیلومتر",
    "price": "۴,۶۵۰,۰۰۰,۰۰۰ تومان",
    "city": "تهران",
    "location": "جنت‌آباد جنوبی",
    "token": "QandF1yc",
    "url": "https://divar.ir/v/QandF1yc",
    "image": "https://s100.divarcdn.com/static/photo/neda/webp_thumbnail/OGWRlSX-8TavKa1mWPgdqg/c619b29e-2164-4bcd-9e3f-8ae3267b2c11.webp"
  },
  {
    "title": "دنا پلاس توربو اتوماتیک آپشنال/1404و1405تحویل فوری",
    "subtitle": "۰ کیلومتر",
    "price": "۱,۸۳۵,۰۰۰,۰۰۰ تومان",
    "city": "تهران",
    "location": "شهرآرا",
    "token": "QaRSnfrT",
    "url": "https://divar.ir/v/QaRSnfrT",
    "image": "https://s100.divarcdn.com/static/photo/neda/webp_thumbnail/G4TT7DE2tdxW1oYN9PcZ-A/f0640ef7-3de1-4c9a-8c2c-8c2c7b9b1850.webp"
  },
  {
    "title": "آریزو 6 جی تی صفر / فروش نقد و اقساط بانکی",
    "subtitle": "۰ کیلومتر",
    "price": "۲,۴۰۰,۰۰۰,۰۰۰ تومان",
    "city": "تهران",
    "location": "ظفر",
    "token": "QadWHXOF",
    "url": "https://divar.ir/v/QadWHXOF",
    "image": "https://s100.divarcdn.com/static/photo/neda/webp_thumbnail/MD9YQ_3WNJDHil-69LGQSQ/63213b13-f9cc-4efb-bb0e-ba957dd119be.jpg.webp"
  },
  {
    "title": "هایما S8 اس8 تنوع رنگ *S7*S5*تحویل فوری1404و 1405",
    "subtitle": "۰ کیلومتر",
    "price": "۳,۳۹۰,۰۰۰,۰۰۰ تومان",
    "city": "تهران",
    "location": "شهرآرا",
    "token": "QaROsZv9",
    "url": "https://divar.ir/v/QaROsZv9",
    "image": "https://s100.divarcdn.com/static/photo/neda/webp_thumbnail/idlW_9zr9e9qzvHEK8K8SQ/7a358fa3-9a6a-44ea-8a7b-4e7567ac3bbe.webp"
  },
  {
    "title": "لندکروز ۲۰۲۵ صفر",
    "subtitle": "۰ کیلومتر",
    "price": "۱,۰۰۰ تومان",
    "city": "تهران",
    "location": "آجودانیه",
    "token": "QadW3RD8",
    "url": "https://divar.ir/v/QadW3RD8",
    "image": "https://s100.divarcdn.com/static/photo/neda/webp_thumbnail/_bAaz9a3WjkJaER6JmYKHQ/16998aa3-3385-4600-b37a-0af69cfe582d.webp"
  },
  {
    "title": "سمند سورن پلاس EF7 دوگانه شرکتی/*مدل1404تحویل روز",
    "subtitle": "۰ کیلومتر",
    "price": "۱,۲۶۰,۰۰۰,۰۰۰ تومان",
    "city": "تهران",
    "location": "شهرآرا",
    "token": "QaRmn6F8",
    "url": "https://divar.ir/v/QaRmn6F8",
    "image": "https://s100.divarcdn.com/static/photo/neda/webp_thumbnail/X81SvN1pAj_XkQRqdL6rHQ/39d4aae0-f402-497c-a57e-a88ff1890c46.webp"
  },
  {
    "title": "تارا اتوماتیک V4 وی4 تنوع رنگ/*مدل1404 تحویل فوری",
    "subtitle": "۰ کیلومتر",
    "price": "۱,۷۲۵,۰۰۰,۰۰۰ تومان",
    "city": "تهران",
    "location": "شهرآرا",
    "token": "QaRKp3lS",
    "url": "https://divar.ir/v/QaRKp3lS",
    "image": "https://s100.divarcdn.com/static/photo/neda/webp_thumbnail/huJM2I5exn_7WXKAuVrEnw/cb42c4ab-a0ff-40f1-94bb-fd44ea9d515b.webp"
  },
  {
    "title": "پژو۲۰۷ اتوماتیک سقف فلز صفر ۱۴۰۴",
    "subtitle": "۰ کیلومتر",
    "price": "۱,۷۹۰,۰۰۰,۰۰۰ تومان",
    "city": "تهران",
    "location": "پاسداران",
    "token": "QadSX-Jb",
    "url": "https://divar.ir/v/QadSX-Jb",
    "image": "https://s100.divarcdn.com/static/photo/neda/webp_thumbnail/FgEpcp5LyfXZSXHT6htWzQ/caaf3773-19df-495e-95fd-464b02a95207.webp"
  },
  {
    "title": "پژو207i دنده ای پانوراما TU5P ارتقا یافته/*1404روز",
    "subtitle": "۰ کیلومتر",
    "price": "۱,۴۴۵,۰۰۰,۰۰۰ تومان",
    "city": "تهران",
    "location": "شهرآرا",
    "token": "QaRWHpjZ",
    "url": "https://divar.ir/v/QaRWHpjZ",
    "image": "https://s100.divarcdn.com/static/photo/neda/webp_thumbnail/zHlGU0a9rbf2F0W58lRjag/bcd2bac1-a1e1-4ea0-9d88-212b1dd3a21c.webp"
  },
  {
    "title": "x77",
    "subtitle": "۰ کیلومتر",
    "price": "۳,۳۹۱,۰۰۰,۰۰۰ تومان",
    "city": "تهران",
    "location": "جنت‌آباد مرکزی",
    "token": "QadWnHyE",
    "url": "https://divar.ir/v/QadWnHyE",
    "image": "https://s100.divarcdn.com/static/photo/neda/webp_thumbnail/tORX1HuPx1tcA-IShG9wxg/d20320f3-d414-4dc5-9f32-8835f0c90130.webp"
  },
  {
    "title": "فروش نقد کی ام سی sr3/تحویل آنی",
    "subtitle": "۰ کیلومتر",
    "price": "۲,۶۵۰,۰۰۰,۰۰۰ تومان",
    "city": "تهران",
    "location": "سردارجنگل",
    "token": "QaGZX2N0",
    "url": "https://divar.ir/v/QaGZX2N0",
    "image": "https://s100.divarcdn.com/static/photo/neda/webp_thumbnail/6pxh-_HQS4ZPB4_h52nqSw/4cdce270-673a-45f5-bd11-19fce6a4e5bd.webp"
  },
  {
    "title": "هایما S7 Pro (تحویل روز سند بنام اقساط بلند مدت)",
    "subtitle": "۰ کیلومتر",
    "price": "۱,۶۰۰,۰۰۰,۰۰۰ تومان",
    "city": "تهران",
    "location": "جمال‌زاده",
    "token": "AaNyviZr",
    "url": "https://divar.ir/v/AaNyviZr",
    "image": "https://s100.divarcdn.com/static/photo/afra/webp_thumbnail/0uHOeJLJLYZx7s2ZW52NWA/ae205a76-159f-41d0-829d-95c0df223a8f.jpg.webp"
  },
  {
    "title": "سمند سورن پلاس دوگانه شرکتی/مدل1404/صفر تحویل آنی",
    "subtitle": "۰ کیلومتر",
    "price": "۱,۲۸۵,۰۰۰,۰۰۰ تومان",
    "city": "تهران",
    "location": "شهرآرا",
    "token": "AaJxiS5o",
    "url": "https://divar.ir/v/AaJxiS5o",
    "image": "https://s100.divarcdn.com/static/photo/neda/webp_thumbnail/TINyRNDVH6H6EzNxkU_c4g/4e4edce6-a46c-428e-abfd-1278c008003b.jpg.webp"
  },
  {
    "title": "فروش اقساط لوکانو ۷ لوکانو ۸ صفر",
    "subtitle": "۰ کیلومتر",
    "price": "۱۰,۰۰۰,۰۰۰ تومان",
    "city": "تهران",
    "location": "المهدی",
    "token": "QaTZIrIU",
    "url": "https://divar.ir/v/QaTZIrIU",
    "image": "https://s100.divarcdn.com/static/photo/neda/webp_thumbnail/UAmSi_7UAafSBdUa16ZI5A/c38b5e02-9825-4403-9e76-a62755866ce5.webp"
  },
  {
    "title": "دنا اتوماتیک اپشنال/دنا ۶دنده",
    "subtitle": "۰ کیلومتر",
    "price": "۱,۶۹۰,۰۰۰,۰۰۰ تومان",
    "city": "تهران",
    "location": "ستارخان",
    "token": "QaJWu0tR",
    "url": "https://divar.ir/v/QaJWu0tR",
    "image": "https://s100.divarcdn.com/static/photo/neda/webp_thumbnail/u1LmRKruj8EwcenK6FWJIg/a806c589-9061-4cb5-8f18-f7a831fb8a11.webp"
  },
  {
    "title": "کوییک gx (تحویل روز سود بانکی نقد و اقساط 36ماهه)",
    "subtitle": "۰ کیلومتر",
    "price": "۴۵۰,۰۰۰,۰۰۰ تومان",
    "city": "تهران",
    "location": "جمال‌زاده",
    "token": "wZ23ylyF",
    "url": "https://divar.ir/v/wZ23ylyF",
    "image": "https://s100.divarcdn.com/static/photo/neda/webp_thumbnail/jjILrLYyreFVE3AOvyutSw/68895283-d92c-4d1b-8efa-a2b465ece5cf.webp"
  },
  {
    "title": "سورن پلاس+ XU7P مدل 1404  تحویل روز",
    "subtitle": "۰ کیلومتر",
    "price": "۱,۱۸۵,۰۰۰,۰۰۰ تومان",
    "city": "تهران",
    "location": "شهرآرا",
    "token": "QabdFo25",
    "url": "https://divar.ir/v/QabdFo25",
    "image": "https://s100.divarcdn.com/static/photo/neda/webp_thumbnail/CpbpDHvaZEOMiOYjfg6XZg/c50eab1d-fe1f-4831-b77e-539cfc27f248.webp"
  },
  {
    "title": "ایکس۳۳ کراس ثبت نام/قیمت کارخانه/x33تحویلفوری",
    "subtitle": "۰ کیلومتر",
    "price": "۱,۴۵۰,۰۰۰,۰۰۰ تومان",
    "city": "تهران",
    "location": "ستارخان",
    "token": "QadWnG2L",
    "url": "https://divar.ir/v/QadWnG2L",
    "image": "https://s100.divarcdn.com/static/photo/neda/webp_thumbnail/KweyRu_wvckyQIQAJmtbxA/02eea128-7b30-4cad-8df8-be37b0c7f332.webp"
  },
  {
    "title": "اکستریم VX QX",
    "subtitle": "۰ کیلومتر",
    "price": "۸,۰۰۰,۰۰۰,۰۰۰ تومان",
    "city": "تهران",
    "location": "جنت‌آباد شمالی",
    "token": "QaQOlEz4",
    "url": "https://divar.ir/v/QaQOlEz4",
    "image": "https://s100.divarcdn.com/static/photo/neda/webp_thumbnail/GZQY_rP2Li6kFtajwbx1Xg/cc310f9a-cc16-446d-bcf8-0bb639e1292f.webp"
  },
  {
    "title": "نیسان قشقایی 2025 موتور (2 لیتری )",
    "subtitle": "۰ کیلومتر",
    "price": "۵,۵۹۵,۰۰۰,۰۰۰ تومان",
    "city": "تهران",
    "location": "جماران (نیاوران)",
    "token": "QaZmHukQ",
    "url": "https://divar.ir/v/QaZmHukQ",
    "image": "https://s100.divarcdn.com/static/photo/neda/webp_thumbnail/cn285610iH_Ih-ZZrTP95Q/f5af513e-3d0d-4010-90fa-2e567fe623c1.webp"
  },
  {
    "title": "کی‌ام‌سی ایگل /kmc eagle، مدل1404",
    "subtitle": "۰ کیلومتر",
    "price": "۱,۸۰۰,۰۰۰,۰۰۰ تومان",
    "city": "تهران",
    "location": "سهروردی",
    "token": "Qa05mkEX",
    "url": "https://divar.ir/v/Qa05mkEX",
    "image": "https://s100.divarcdn.com/static/photo/neda/webp_thumbnail/yULUcZhfGZ-2EyyRxEmU7Q/c07d4080-6f2b-4876-ba8a-e93f7a59b651.webp"
  },
  {
    "title": "هایما x7اقساط بانکی/تحویل لحظه/اقساط۵ساله",
    "subtitle": "۰ کیلومتر",
    "price": "۱,۳۷۰,۰۰۰,۰۰۰,۰۰۰ تومان",
    "city": "تهران",
    "location": "جنت‌آباد جنوبی",
    "token": "QaUODhgT",
    "url": "https://divar.ir/v/QaUODhgT",
    "image": "https://s100.divarcdn.com/static/photo/neda/webp_thumbnail/L_diKHzMWtoFeXLZDGTXkw/0af2a432-57a6-40c3-b346-f86679ada948.webp"
  },
  {
    "title": "ریرا ایران خودرو ری‌ را توربو/1404و1405تحویل فوری",
    "subtitle": "۰ کیلومتر",
    "price": "۲,۳۶۵,۰۰۰,۰۰۰ تومان",
    "city": "تهران",
    "location": "شهرآرا",
    "token": "QaRi3B2p",
    "url": "https://divar.ir/v/QaRi3B2p",
    "image": "https://s100.divarcdn.com/static/photo/neda/webp_thumbnail/29QAJL6d4pe624VA9bUfkg/abe33801-c3a1-459a-8144-3f0819779aa2.webp"
  },
  {
    "title": "دیگنیتی پرایم Prime داخل مشکی*مارون/*1404صفر روز",
    "subtitle": "۰ کیلومتر",
    "price": "۳,۴۲۵,۰۰۰,۰۰۰ تومان",
    "city": "تهران",
    "location": "شهرآرا",
    "token": "QaVu5g51",
    "url": "https://divar.ir/v/QaVu5g51",
    "image": "https://s100.divarcdn.com/static/photo/neda/webp_thumbnail/iZakerAJsEeHLbw38_aaQg/7455f185-8d83-46c5-8e54-19c8d0bad57c.webp"
  },
  {
    "title": "207 پانوراما اتومات سقف شیشه ای TU5P صفر 1404",
    "subtitle": "۰ کیلومتر",
    "price": "۱,۷۷۰,۰۰۰,۰۰۰ تومان",
    "city": "تهران",
    "location": "فردوس",
    "token": "QasN6Vt0",
    "url": "https://divar.ir/v/QasN6Vt0",
    "image": "https://s100.divarcdn.com/static/photo/neda/webp_thumbnail/3q4HydGhJXu28lR9aaWujA/a1544b86-86e1-4cc4-9ee9-6d40b481f93f.webp"
  },
  {
    "title": "تویوتا لوین بنزینی ۱۲۰۰ توربو ۲۰۲۴ صفر خشک",
    "subtitle": "۰ کیلومتر",
    "price": "۴,۶۵۰,۰۰۰,۰۰۰ تومان",
    "city": "تهران",
    "location": "جنت‌آباد جنوبی",
    "token": "QandF1yc",
    "url": "https://divar.ir/v/QandF1yc",
    "image": "https://s100.divarcdn.com/static/photo/neda/webp_thumbnail/OGWRlSX-8TavKa1mWPgdqg/c619b29e-2164-4bcd-9e3f-8ae3267b2c11.webp"
  },
  {
    "title": "دنا پلاس توربو اتوماتیک آپشنال/1404و1405تحویل فوری",
    "subtitle": "۰ کیلومتر",
    "price": "۱,۸۳۵,۰۰۰,۰۰۰ تومان",
    "city": "تهران",
    "location": "شهرآرا",
    "token": "QaRSnfrT",
    "url": "https://divar.ir/v/QaRSnfrT",
    "image": "https://s100.divarcdn.com/static/photo/neda/webp_thumbnail/G4TT7DE2tdxW1oYN9PcZ-A/f0640ef7-3de1-4c9a-8c2c-8c2c7b9b1850.webp"
  },
  {
    "title": "آریزو 6 جی تی صفر / فروش نقد و اقساط بانکی",
    "subtitle": "۰ کیلومتر",
    "price": "۲,۴۰۰,۰۰۰,۰۰۰ تومان",
    "city": "تهران",
    "location": "ظفر",
    "token": "QadWHXOF",
    "url": "https://divar.ir/v/QadWHXOF",
    "image": "https://s100.divarcdn.com/static/photo/neda/webp_thumbnail/MD9YQ_3WNJDHil-69LGQSQ/63213b13-f9cc-4efb-bb0e-ba957dd119be.jpg.webp"
  },
  {
    "title": "هایما S8 اس8 تنوع رنگ *S7*S5*تحویل فوری1404و 1405",
    "subtitle": "۰ کیلومتر",
    "price": "۳,۳۹۰,۰۰۰,۰۰۰ تومان",
    "city": "تهران",
    "location": "شهرآرا",
    "token": "QaROsZv9",
    "url": "https://divar.ir/v/QaROsZv9",
    "image": "https://s100.divarcdn.com/static/photo/neda/webp_thumbnail/idlW_9zr9e9qzvHEK8K8SQ/7a358fa3-9a6a-44ea-8a7b-4e7567ac3bbe.webp"
  },
  {
    "title": "لندکروز ۲۰۲۵ صفر",
    "subtitle": "۰ کیلومتر",
    "price": "۱,۰۰۰ تومان",
    "city": "تهران",
    "location": "آجودانیه",
    "token": "QadW3RD8",
    "url": "https://divar.ir/v/QadW3RD8",
    "image": "https://s100.divarcdn.com/static/photo/neda/webp_thumbnail/_bAaz9a3WjkJaER6JmYKHQ/16998aa3-3385-4600-b37a-0af69cfe582d.webp"
  },
  {
    "title": "سمند سورن پلاس EF7 دوگانه شرکتی/*مدل1404تحویل روز",
    "subtitle": "۰ کیلومتر",
    "price": "۱,۲۶۰,۰۰۰,۰۰۰ تومان",
    "city": "تهران",
    "location": "شهرآرا",
    "token": "QaRmn6F8",
    "url": "https://divar.ir/v/QaRmn6F8",
    "image": "https://s100.divarcdn.com/static/photo/neda/webp_thumbnail/X81SvN1pAj_XkQRqdL6rHQ/39d4aae0-f402-497c-a57e-a88ff1890c46.webp"
  },
  {
    "title": "تارا اتوماتیک V4 وی4 تنوع رنگ/*مدل1404 تحویل فوری",
    "subtitle": "۰ کیلومتر",
    "price": "۱,۷۲۵,۰۰۰,۰۰۰ تومان",
    "city": "تهران",
    "location": "شهرآرا",
    "token": "QaRKp3lS",
    "url": "https://divar.ir/v/QaRKp3lS",
    "image": "https://s100.divarcdn.com/static/photo/neda/webp_thumbnail/huJM2I5exn_7WXKAuVrEnw/cb42c4ab-a0ff-40f1-94bb-fd44ea9d515b.webp"
  },
  {
    "title": "پژو۲۰۷ اتوماتیک سقف فلز صفر ۱۴۰۴",
    "subtitle": "۰ کیلومتر",
    "price": "۱,۷۹۰,۰۰۰,۰۰۰ تومان",
    "city": "تهران",
    "location": "پاسداران",
    "token": "QadSX-Jb",
    "url": "https://divar.ir/v/QadSX-Jb",
    "image": "https://s100.divarcdn.com/static/photo/neda/webp_thumbnail/FgEpcp5LyfXZSXHT6htWzQ/caaf3773-19df-495e-95fd-464b02a95207.webp"
  },
  {
    "title": "پژو207i دنده ای پانوراما TU5P ارتقا یافته/*1404روز",
    "subtitle": "۰ کیلومتر",
    "price": "۱,۴۴۵,۰۰۰,۰۰۰ تومان",
    "city": "تهران",
    "location": "شهرآرا",
    "token": "QaRWHpjZ",
    "url": "https://divar.ir/v/QaRWHpjZ",
    "image": "https://s100.divarcdn.com/static/photo/neda/webp_thumbnail/zHlGU0a9rbf2F0W58lRjag/bcd2bac1-a1e1-4ea0-9d88-212b1dd3a21c.webp"
  },
  {
    "title": "x77",
    "subtitle": "۰ کیلومتر",
    "price": "۳,۳۹۱,۰۰۰,۰۰۰ تومان",
    "city": "تهران",
    "location": "جنت‌آباد مرکزی",
    "token": "QadWnHyE",
    "url": "https://divar.ir/v/QadWnHyE",
    "image": "https://s100.divarcdn.com/static/photo/neda/webp_thumbnail/tORX1HuPx1tcA-IShG9wxg/d20320f3-d414-4dc5-9f32-8835f0c90130.webp"
  },
  {
    "title": "فروش نقد کی ام سی sr3/تحویل آنی",
    "subtitle": "۰ کیلومتر",
    "price": "۲,۶۵۰,۰۰۰,۰۰۰ تومان",
    "city": "تهران",
    "location": "سردارجنگل",
    "token": "QaGZX2N0",
    "url": "https://divar.ir/v/QaGZX2N0",
    "image": "https://s100.divarcdn.com/static/photo/neda/webp_thumbnail/6pxh-_HQS4ZPB4_h52nqSw/4cdce270-673a-45f5-bd11-19fce6a4e5bd.webp"
  },
  {
    "title": "هایما S7 Pro (تحویل روز سند بنام اقساط بلند مدت)",
    "subtitle": "۰ کیلومتر",
    "price": "۱,۶۰۰,۰۰۰,۰۰۰ تومان",
    "city": "تهران",
    "location": "جمال‌زاده",
    "token": "AaNyviZr",
    "url": "https://divar.ir/v/AaNyviZr",
    "image": "https://s100.divarcdn.com/static/photo/afra/webp_thumbnail/0uHOeJLJLYZx7s2ZW52NWA/ae205a76-159f-41d0-829d-95c0df223a8f.jpg.webp"
  },
  {
    "title": "سمند سورن پلاس دوگانه شرکتی/مدل1404/صفر تحویل آنی",
    "subtitle": "۰ کیلومتر",
    "price": "۱,۲۸۵,۰۰۰,۰۰۰ تومان",
    "city": "تهران",
    "location": "شهرآرا",
    "token": "AaJxiS5o",
    "url": "https://divar.ir/v/AaJxiS5o",
    "image": "https://s100.divarcdn.com/static/photo/neda/webp_thumbnail/TINyRNDVH6H6EzNxkU_c4g/4e4edce6-a46c-428e-abfd-1278c008003b.jpg.webp"
  },
  {
    "title": "فروش اقساط لوکانو ۷ لوکانو ۸ صفر",
    "subtitle": "۰ کیلومتر",
    "price": "۱۰,۰۰۰,۰۰۰ تومان",
    "city": "تهران",
    "location": "المهدی",
    "token": "QaTZIrIU",
    "url": "https://divar.ir/v/QaTZIrIU",
    "image": "https://s100.divarcdn.com/static/photo/neda/webp_thumbnail/UAmSi_7UAafSBdUa16ZI5A/c38b5e02-9825-4403-9e76-a62755866ce5.webp"
  },
  {
    "title": "دنا اتوماتیک اپشنال/دنا ۶دنده",
    "subtitle": "۰ کیلومتر",
    "price": "۱,۶۹۰,۰۰۰,۰۰۰ تومان",
    "city": "تهران",
    "location": "ستارخان",
    "token": "QaJWu0tR",
    "url": "https://divar.ir/v/QaJWu0tR",
    "image": "https://s100.divarcdn.com/static/photo/neda/webp_thumbnail/u1LmRKruj8EwcenK6FWJIg/a806c589-9061-4cb5-8f18-f7a831fb8a11.webp"
  },
  {
    "title": "کوییک gx (تحویل روز سود بانکی نقد و اقساط 36ماهه)",
    "subtitle": "۰ کیلومتر",
    "price": "۴۵۰,۰۰۰,۰۰۰ تومان",
    "city": "تهران",
    "location": "جمال‌زاده",
    "token": "wZ23ylyF",
    "url": "https://divar.ir/v/wZ23ylyF",
    "image": "https://s100.divarcdn.com/static/photo/neda/webp_thumbnail/jjILrLYyreFVE3AOvyutSw/68895283-d92c-4d1b-8efa-a2b465ece5cf.webp"
  },
  {
    "title": "سورن پلاس+ XU7P مدل 1404  تحویل روز",
    "subtitle": "۰ کیلومتر",
    "price": "۱,۱۸۵,۰۰۰,۰۰۰ تومان",
    "city": "تهران",
    "location": "شهرآرا",
    "token": "QabdFo25",
    "url": "https://divar.ir/v/QabdFo25",
    "image": "https://s100.divarcdn.com/static/photo/neda/webp_thumbnail/CpbpDHvaZEOMiOYjfg6XZg/c50eab1d-fe1f-4831-b77e-539cfc27f248.webp"
  },
  {
    "title": "اکستریم VX QX",
    "subtitle": "۰ کیلومتر",
    "price": "۸,۰۰۰,۰۰۰,۰۰۰ تومان",
    "city": "تهران",
    "location": "جنت‌آباد شمالی",
    "token": "QaQOlEz4",
    "url": "https://divar.ir/v/QaQOlEz4",
    "image": "https://s100.divarcdn.com/static/photo/neda/webp_thumbnail/GZQY_rP2Li6kFtajwbx1Xg/cc310f9a-cc16-446d-bcf8-0bb639e1292f.webp"
  },
  {
    "title": "نیسان قشقایی 2025 موتور (2 لیتری )",
    "subtitle": "۰ کیلومتر",
    "price": "۵,۵۹۵,۰۰۰,۰۰۰ تومان",
    "city": "تهران",
    "location": "جماران (نیاوران)",
    "token": "QaZmHukQ",
    "url": "https://divar.ir/v/QaZmHukQ",
    "image": "https://s100.divarcdn.com/static/photo/neda/webp_thumbnail/cn285610iH_Ih-ZZrTP95Q/f5af513e-3d0d-4010-90fa-2e567fe623c1.webp"
  },
  {
    "title": "کی‌ام‌سی ایگل /kmc eagle، مدل1404",
    "subtitle": "۰ کیلومتر",
    "price": "۱,۸۰۰,۰۰۰,۰۰۰ تومان",
    "city": "تهران",
    "location": "سهروردی",
    "token": "Qa05mkEX",
    "url": "https://divar.ir/v/Qa05mkEX",
    "image": "https://s100.divarcdn.com/static/photo/neda/webp_thumbnail/yULUcZhfGZ-2EyyRxEmU7Q/c07d4080-6f2b-4876-ba8a-e93f7a59b651.webp"
  },
  {
    "title": "هایما x7اقساط بانکی/تحویل لحظه/اقساط۵ساله",
    "subtitle": "۰ کیلومتر",
    "price": "۱,۳۷۰,۰۰۰,۰۰۰,۰۰۰ تومان",
    "city": "تهران",
    "location": "جنت‌آباد جنوبی",
    "token": "QaUODhgT",
    "url": "https://divar.ir/v/QaUODhgT",
    "image": "https://s100.divarcdn.com/static/photo/neda/webp_thumbnail/L_diKHzMWtoFeXLZDGTXkw/0af2a432-57a6-40c3-b346-f86679ada948.webp"
  },
  {
    "title": "ریرا ایران خودرو ری‌ را توربو/1404و1405تحویل فوری",
    "subtitle": "۰ کیلومتر",
    "price": "۲,۳۶۵,۰۰۰,۰۰۰ تومان",
    "city": "تهران",
    "location": "شهرآرا",
    "token": "QaRi3B2p",
    "url": "https://divar.ir/v/QaRi3B2p",
    "image": "https://s100.divarcdn.com/static/photo/neda/webp_thumbnail/29QAJL6d4pe624VA9bUfkg/abe33801-c3a1-459a-8144-3f0819779aa2.webp"
  },
  {
    "title": "دیگنیتی پرایم Prime داخل مشکی*مارون/*1404صفر روز",
    "subtitle": "۰ کیلومتر",
    "price": "۳,۴۲۵,۰۰۰,۰۰۰ تومان",
    "city": "تهران",
    "location": "شهرآرا",
    "token": "QaVu5g51",
    "url": "https://divar.ir/v/QaVu5g51",
    "image": "https://s100.divarcdn.com/static/photo/neda/webp_thumbnail/iZakerAJsEeHLbw38_aaQg/7455f185-8d83-46c5-8e54-19c8d0bad57c.webp"
  },
  {
    "title": "207 پانوراما اتومات سقف شیشه ای TU5P صفر 1404",
    "subtitle": "۰ کیلومتر",
    "price": "۱,۷۷۰,۰۰۰,۰۰۰ تومان",
    "city": "تهران",
    "location": "فردوس",
    "token": "QasN6Vt0",
    "url": "https://divar.ir/v/QasN6Vt0",
    "image": "https://s100.divarcdn.com/static/photo/neda/webp_thumbnail/3q4HydGhJXu28lR9aaWujA/a1544b86-86e1-4cc4-9ee9-6d40b481f93f.webp"
  },
  {
    "title": "تویوتا لوین بنزینی ۱۲۰۰ توربو ۲۰۲۴ صفر خشک",
    "subtitle": "۰ کیلومتر",
    "price": "۴,۶۵۰,۰۰۰,۰۰۰ تومان",
    "city": "تهران",
    "location": "جنت‌آباد جنوبی",
    "token": "QandF1yc",
    "url": "https://divar.ir/v/QandF1yc",
    "image": "https://s100.divarcdn.com/static/photo/neda/webp_thumbnail/OGWRlSX-8TavKa1mWPgdqg/c619b29e-2164-4bcd-9e3f-8ae3267b2c11.webp"
  },
  {
    "title": "دنا پلاس توربو اتوماتیک آپشنال/1404و1405تحویل فوری",
    "subtitle": "۰ کیلومتر",
    "price": "۱,۸۳۵,۰۰۰,۰۰۰ تومان",
    "city": "تهران",
    "location": "شهرآرا",
    "token": "QaRSnfrT",
    "url": "https://divar.ir/v/QaRSnfrT",
    "image": "https://s100.divarcdn.com/static/photo/neda/webp_thumbnail/G4TT7DE2tdxW1oYN9PcZ-A/f0640ef7-3de1-4c9a-8c2c-8c2c7b9b1850.webp"
  },
  {
    "title": "آریزو 6 جی تی صفر / فروش نقد و اقساط بانکی",
    "subtitle": "۰ کیلومتر",
    "price": "۲,۴۰۰,۰۰۰,۰۰۰ تومان",
    "city": "تهران",
    "location": "ظفر",
    "token": "QadWHXOF",
    "url": "https://divar.ir/v/QadWHXOF",
    "image": "https://s100.divarcdn.com/static/photo/neda/webp_thumbnail/MD9YQ_3WNJDHil-69LGQSQ/63213b13-f9cc-4efb-bb0e-ba957dd119be.jpg.webp"
  },
  {
    "title": "هایما S8 اس8 تنوع رنگ *S7*S5*تحویل فوری1404و 1405",
    "subtitle": "۰ کیلومتر",
    "price": "۳,۳۹۰,۰۰۰,۰۰۰ تومان",
    "city": "تهران",
    "location": "شهرآرا",
    "token": "QaROsZv9",
    "url": "https://divar.ir/v/QaROsZv9",
    "image": "https://s100.divarcdn.com/static/photo/neda/webp_thumbnail/idlW_9zr9e9qzvHEK8K8SQ/7a358fa3-9a6a-44ea-8a7b-4e7567ac3bbe.webp"
  },
  {
    "title": "لندکروز ۲۰۲۵ صفر",
    "subtitle": "۰ کیلومتر",
    "price": "۱,۰۰۰ تومان",
    "city": "تهران",
    "location": "آجودانیه",
    "token": "QadW3RD8",
    "url": "https://divar.ir/v/QadW3RD8",
    "image": "https://s100.divarcdn.com/static/photo/neda/webp_thumbnail/_bAaz9a3WjkJaER6JmYKHQ/16998aa3-3385-4600-b37a-0af69cfe582d.webp"
  },
  {
    "title": "سمند سورن پلاس EF7 دوگانه شرکتی/*مدل1404تحویل روز",
    "subtitle": "۰ کیلومتر",
    "price": "۱,۲۶۰,۰۰۰,۰۰۰ تومان",
    "city": "تهران",
    "location": "شهرآرا",
    "token": "QaRmn6F8",
    "url": "https://divar.ir/v/QaRmn6F8",
    "image": "https://s100.divarcdn.com/static/photo/neda/webp_thumbnail/X81SvN1pAj_XkQRqdL6rHQ/39d4aae0-f402-497c-a57e-a88ff1890c46.webp"
  },
  {
    "title": "تارا اتوماتیک V4 وی4 تنوع رنگ/*مدل1404 تحویل فوری",
    "subtitle": "۰ کیلومتر",
    "price": "۱,۷۲۵,۰۰۰,۰۰۰ تومان",
    "city": "تهران",
    "location": "شهرآرا",
    "token": "QaRKp3lS",
    "url": "https://divar.ir/v/QaRKp3lS",
    "image": "https://s100.divarcdn.com/static/photo/neda/webp_thumbnail/huJM2I5exn_7WXKAuVrEnw/cb42c4ab-a0ff-40f1-94bb-fd44ea9d515b.webp"
  },
  {
    "title": "پژو۲۰۷ اتوماتیک سقف فلز صفر ۱۴۰۴",
    "subtitle": "۰ کیلومتر",
    "price": "۱,۷۹۰,۰۰۰,۰۰۰ تومان",
    "city": "تهران",
    "location": "پاسداران",
    "token": "QadSX-Jb",
    "url": "https://divar.ir/v/QadSX-Jb",
    "image": "https://s100.divarcdn.com/static/photo/neda/webp_thumbnail/FgEpcp5LyfXZSXHT6htWzQ/caaf3773-19df-495e-95fd-464b02a95207.webp"
  },
  {
    "title": "پژو207i دنده ای پانوراما TU5P ارتقا یافته/*1404روز",
    "subtitle": "۰ کیلومتر",
    "price": "۱,۴۴۵,۰۰۰,۰۰۰ تومان",
    "city": "تهران",
    "location": "شهرآرا",
    "token": "QaRWHpjZ",
    "url": "https://divar.ir/v/QaRWHpjZ",
    "image": "https://s100.divarcdn.com/static/photo/neda/webp_thumbnail/zHlGU0a9rbf2F0W58lRjag/bcd2bac1-a1e1-4ea0-9d88-212b1dd3a21c.webp"
  },
  {
    "title": "x77",
    "subtitle": "۰ کیلومتر",
    "price": "۳,۳۹۱,۰۰۰,۰۰۰ تومان",
    "city": "تهران",
    "location": "جنت‌آباد مرکزی",
    "token": "QadWnHyE",
    "url": "https://divar.ir/v/QadWnHyE",
    "image": "https://s100.divarcdn.com/static/photo/neda/webp_thumbnail/tORX1HuPx1tcA-IShG9wxg/d20320f3-d414-4dc5-9f32-8835f0c90130.webp"
  },
  {
    "title": "فروش نقد کی ام سی sr3/تحویل آنی",
    "subtitle": "۰ کیلومتر",
    "price": "۲,۶۵۰,۰۰۰,۰۰۰ تومان",
    "city": "تهران",
    "location": "سردارجنگل",
    "token": "QaGZX2N0",
    "url": "https://divar.ir/v/QaGZX2N0",
    "image": "https://s100.divarcdn.com/static/photo/neda/webp_thumbnail/6pxh-_HQS4ZPB4_h52nqSw/4cdce270-673a-45f5-bd11-19fce6a4e5bd.webp"
  },
  {
    "title": "هایما S7 Pro (تحویل روز سند بنام اقساط بلند مدت)",
    "subtitle": "۰ کیلومتر",
    "price": "۱,۶۰۰,۰۰۰,۰۰۰ تومان",
    "city": "تهران",
    "location": "جمال‌زاده",
    "token": "AaNyviZr",
    "url": "https://divar.ir/v/AaNyviZr",
    "image": "https://s100.divarcdn.com/static/photo/afra/webp_thumbnail/0uHOeJLJLYZx7s2ZW52NWA/ae205a76-159f-41d0-829d-95c0df223a8f.jpg.webp"
  },
  {
    "title": "سمند سورن پلاس دوگانه شرکتی/مدل1404/صفر تحویل آنی",
    "subtitle": "۰ کیلومتر",
    "price": "۱,۲۸۵,۰۰۰,۰۰۰ تومان",
    "city": "تهران",
    "location": "شهرآرا",
    "token": "AaJxiS5o",
    "url": "https://divar.ir/v/AaJxiS5o",
    "image": "https://s100.divarcdn.com/static/photo/neda/webp_thumbnail/TINyRNDVH6H6EzNxkU_c4g/4e4edce6-a46c-428e-abfd-1278c008003b.jpg.webp"
  },
  {
    "title": "فروش اقساط لوکانو ۷ لوکانو ۸ صفر",
    "subtitle": "۰ کیلومتر",
    "price": "۱۰,۰۰۰,۰۰۰ تومان",
    "city": "تهران",
    "location": "المهدی",
    "token": "QaTZIrIU",
    "url": "https://divar.ir/v/QaTZIrIU",
    "image": "https://s100.divarcdn.com/static/photo/neda/webp_thumbnail/UAmSi_7UAafSBdUa16ZI5A/c38b5e02-9825-4403-9e76-a62755866ce5.webp"
  },
  {
    "title": "دنا اتوماتیک اپشنال/دنا ۶دنده",
    "subtitle": "۰ کیلومتر",
    "price": "۱,۶۹۰,۰۰۰,۰۰۰ تومان",
    "city": "تهران",
    "location": "ستارخان",
    "token": "QaJWu0tR",
    "url": "https://divar.ir/v/QaJWu0tR",
    "image": "https://s100.divarcdn.com/static/photo/neda/webp_thumbnail/u1LmRKruj8EwcenK6FWJIg/a806c589-9061-4cb5-8f18-f7a831fb8a11.webp"
  },
  {
    "title": "کوییک gx (تحویل روز سود بانکی نقد و اقساط 36ماهه)",
    "subtitle": "۰ کیلومتر",
    "price": "۴۵۰,۰۰۰,۰۰۰ تومان",
    "city": "تهران",
    "location": "جمال‌زاده",
    "token": "wZ23ylyF",
    "url": "https://divar.ir/v/wZ23ylyF",
    "image": "https://s100.divarcdn.com/static/photo/neda/webp_thumbnail/jjILrLYyreFVE3AOvyutSw/68895283-d92c-4d1b-8efa-a2b465ece5cf.webp"
  },
  {
    "title": "سورن پلاس+ XU7P مدل 1404  تحویل روز",
    "subtitle": "۰ کیلومتر",
    "price": "۱,۱۸۵,۰۰۰,۰۰۰ تومان",
    "city": "تهران",
    "location": "شهرآرا",
    "token": "QabdFo25",
    "url": "https://divar.ir/v/QabdFo25",
    "image": "https://s100.divarcdn.com/static/photo/neda/webp_thumbnail/CpbpDHvaZEOMiOYjfg6XZg/c50eab1d-fe1f-4831-b77e-539cfc27f248.webp"
  },
  {
    "title": "اکستریم VX QX",
    "subtitle": "۰ کیلومتر",
    "price": "۸,۰۰۰,۰۰۰,۰۰۰ تومان",
    "city": "تهران",
    "location": "جنت‌آباد شمالی",
    "token": "QaQOlEz4",
    "url": "https://divar.ir/v/QaQOlEz4",
    "image": "https://s100.divarcdn.com/static/photo/neda/webp_thumbnail/GZQY_rP2Li6kFtajwbx1Xg/cc310f9a-cc16-446d-bcf8-0bb639e1292f.webp"
  },
  {
    "title": "نیسان قشقایی 2025 موتور (2 لیتری )",
    "subtitle": "۰ کیلومتر",
    "price": "۵,۵۹۵,۰۰۰,۰۰۰ تومان",
    "city": "تهران",
    "location": "جماران (نیاوران)",
    "token": "QaZmHukQ",
    "url": "https://divar.ir/v/QaZmHukQ",
    "image": "https://s100.divarcdn.com/static/photo/neda/webp_thumbnail/cn285610iH_Ih-ZZrTP95Q/f5af513e-3d0d-4010-90fa-2e567fe623c1.webp"
  },
  {
    "title": "کی‌ام‌سی ایگل /kmc eagle، مدل1404",
    "subtitle": "۰ کیلومتر",
    "price": "۱,۸۰۰,۰۰۰,۰۰۰ تومان",
    "city": "تهران",
    "location": "سهروردی",
    "token": "Qa05mkEX",
    "url": "https://divar.ir/v/Qa05mkEX",
    "image": "https://s100.divarcdn.com/static/photo/neda/webp_thumbnail/yULUcZhfGZ-2EyyRxEmU7Q/c07d4080-6f2b-4876-ba8a-e93f7a59b651.webp"
  },
  {
    "title": "هایما x7اقساط بانکی/تحویل لحظه/اقساط۵ساله",
    "subtitle": "۰ کیلومتر",
    "price": "۱,۳۷۰,۰۰۰,۰۰۰,۰۰۰ تومان",
    "city": "تهران",
    "location": "جنت‌آباد جنوبی",
    "token": "QaUODhgT",
    "url": "https://divar.ir/v/QaUODhgT",
    "image": "https://s100.divarcdn.com/static/photo/neda/webp_thumbnail/L_diKHzMWtoFeXLZDGTXkw/0af2a432-57a6-40c3-b346-f86679ada948.webp"
  },
  {
    "title": "ریرا ایران خودرو ری‌ را توربو/1404و1405تحویل فوری",
    "subtitle": "۰ کیلومتر",
    "price": "۲,۳۶۵,۰۰۰,۰۰۰ تومان",
    "city": "تهران",
    "location": "شهرآرا",
    "token": "QaRi3B2p",
    "url": "https://divar.ir/v/QaRi3B2p",
    "image": "https://s100.divarcdn.com/static/photo/neda/webp_thumbnail/29QAJL6d4pe624VA9bUfkg/abe33801-c3a1-459a-8144-3f0819779aa2.webp"
  },
  {
    "title": "دیگنیتی پرایم Prime داخل مشکی*مارون/*1404صفر روز",
    "subtitle": "۰ کیلومتر",
    "price": "۳,۴۲۵,۰۰۰,۰۰۰ تومان",
    "city": "تهران",
    "location": "شهرآرا",
    "token": "QaVu5g51",
    "url": "https://divar.ir/v/QaVu5g51",
    "image": "https://s100.divarcdn.com/static/photo/neda/webp_thumbnail/iZakerAJsEeHLbw38_aaQg/7455f185-8d83-46c5-8e54-19c8d0bad57c.webp"
  },
  {
    "title": "207 پانوراما اتومات سقف شیشه ای TU5P صفر 1404",
    "subtitle": "۰ کیلومتر",
    "price": "۱,۷۷۰,۰۰۰,۰۰۰ تومان",
    "city": "تهران",
    "location": "فردوس",
    "token": "QasN6Vt0",
    "url": "https://divar.ir/v/QasN6Vt0",
    "image": "https://s100.divarcdn.com/static/photo/neda/webp_thumbnail/3q4HydGhJXu28lR9aaWujA/a1544b86-86e1-4cc4-9ee9-6d40b481f93f.webp"
  },
  {
    "title": "تویوتا لوین بنزینی ۱۲۰۰ توربو ۲۰۲۴ صفر خشک",
    "subtitle": "۰ کیلومتر",
    "price": "۴,۶۵۰,۰۰۰,۰۰۰ تومان",
    "city": "تهران",
    "location": "جنت‌آباد جنوبی",
    "token": "QandF1yc",
    "url": "https://divar.ir/v/QandF1yc",
    "image": "https://s100.divarcdn.com/static/photo/neda/webp_thumbnail/OGWRlSX-8TavKa1mWPgdqg/c619b29e-2164-4bcd-9e3f-8ae3267b2c11.webp"
  },
  {
    "title": "دنا پلاس توربو اتوماتیک آپشنال/1404و1405تحویل فوری",
    "subtitle": "۰ کیلومتر",
    "price": "۱,۸۳۵,۰۰۰,۰۰۰ تومان",
    "city": "تهران",
    "location": "شهرآرا",
    "token": "QaRSnfrT",
    "url": "https://divar.ir/v/QaRSnfrT",
    "image": "https://s100.divarcdn.com/static/photo/neda/webp_thumbnail/G4TT7DE2tdxW1oYN9PcZ-A/f0640ef7-3de1-4c9a-8c2c-8c2c7b9b1850.webp"
  },
  {
    "title": "آریزو 6 جی تی صفر / فروش نقد و اقساط بانکی",
    "subtitle": "۰ کیلومتر",
    "price": "۲,۴۰۰,۰۰۰,۰۰۰ تومان",
    "city": "تهران",
    "location": "ظفر",
    "token": "QadWHXOF",
    "url": "https://divar.ir/v/QadWHXOF",
    "image": "https://s100.divarcdn.com/static/photo/neda/webp_thumbnail/MD9YQ_3WNJDHil-69LGQSQ/63213b13-f9cc-4efb-bb0e-ba957dd119be.jpg.webp"
  },
  {
    "title": "هایما S8 اس8 تنوع رنگ *S7*S5*تحویل فوری1404و 1405",
    "subtitle": "۰ کیلومتر",
    "price": "۳,۳۹۰,۰۰۰,۰۰۰ تومان",
    "city": "تهران",
    "location": "شهرآرا",
    "token": "QaROsZv9",
    "url": "https://divar.ir/v/QaROsZv9",
    "image": "https://s100.divarcdn.com/static/photo/neda/webp_thumbnail/idlW_9zr9e9qzvHEK8K8SQ/7a358fa3-9a6a-44ea-8a7b-4e7567ac3bbe.webp"
  },
  {
    "title": "لندکروز ۲۰۲۵ صفر",
    "subtitle": "۰ کیلومتر",
    "price": "۱,۰۰۰ تومان",
    "city": "تهران",
    "location": "آجودانیه",
    "token": "QadW3RD8",
    "url": "https://divar.ir/v/QadW3RD8",
    "image": "https://s100.divarcdn.com/static/photo/neda/webp_thumbnail/_bAaz9a3WjkJaER6JmYKHQ/16998aa3-3385-4600-b37a-0af69cfe582d.webp"
  },
  {
    "title": "سمند سورن پلاس EF7 دوگانه شرکتی/*مدل1404تحویل روز",
    "subtitle": "۰ کیلومتر",
    "price": "۱,۲۶۰,۰۰۰,۰۰۰ تومان",
    "city": "تهران",
    "location": "شهرآرا",
    "token": "QaRmn6F8",
    "url": "https://divar.ir/v/QaRmn6F8",
    "image": "https://s100.divarcdn.com/static/photo/neda/webp_thumbnail/X81SvN1pAj_XkQRqdL6rHQ/39d4aae0-f402-497c-a57e-a88ff1890c46.webp"
  },
  {
    "title": "تارا اتوماتیک V4 وی4 تنوع رنگ/*مدل1404 تحویل فوری",
    "subtitle": "۰ کیلومتر",
    "price": "۱,۷۲۵,۰۰۰,۰۰۰ تومان",
    "city": "تهران",
    "location": "شهرآرا",
    "token": "QaRKp3lS",
    "url": "https://divar.ir/v/QaRKp3lS",
    "image": "https://s100.divarcdn.com/static/photo/neda/webp_thumbnail/huJM2I5exn_7WXKAuVrEnw/cb42c4ab-a0ff-40f1-94bb-fd44ea9d515b.webp"
  },
  {
    "title": "پژو۲۰۷ اتوماتیک سقف فلز صفر ۱۴۰۴",
    "subtitle": "۰ کیلومتر",
    "price": "۱,۷۹۰,۰۰۰,۰۰۰ تومان",
    "city": "تهران",
    "location": "پاسداران",
    "token": "QadSX-Jb",
    "url": "https://divar.ir/v/QadSX-Jb",
    "image": "https://s100.divarcdn.com/static/photo/neda/webp_thumbnail/FgEpcp5LyfXZSXHT6htWzQ/caaf3773-19df-495e-95fd-464b02a95207.webp"
  },
  {
    "title": "پژو207i دنده ای پانوراما TU5P ارتقا یافته/*1404روز",
    "subtitle": "۰ کیلومتر",
    "price": "۱,۴۴۵,۰۰۰,۰۰۰ تومان",
    "city": "تهران",
    "location": "شهرآرا",
    "token": "QaRWHpjZ",
    "url": "https://divar.ir/v/QaRWHpjZ",
    "image": "https://s100.divarcdn.com/static/photo/neda/webp_thumbnail/zHlGU0a9rbf2F0W58lRjag/bcd2bac1-a1e1-4ea0-9d88-212b1dd3a21c.webp"
  },
  {
    "title": "x77",
    "subtitle": "۰ کیلومتر",
    "price": "۳,۳۹۱,۰۰۰,۰۰۰ تومان",
    "city": "تهران",
    "location": "جنت‌آباد مرکزی",
    "token": "QadWnHyE",
    "url": "https://divar.ir/v/QadWnHyE",
    "image": "https://s100.divarcdn.com/static/photo/neda/webp_thumbnail/tORX1HuPx1tcA-IShG9wxg/d20320f3-d414-4dc5-9f32-8835f0c90130.webp"
  },
  {
    "title": "فروش نقد کی ام سی sr3/تحویل آنی",
    "subtitle": "۰ کیلومتر",
    "price": "۲,۶۵۰,۰۰۰,۰۰۰ تومان",
    "city": "تهران",
    "location": "سردارجنگل",
    "token": "QaGZX2N0",
    "url": "https://divar.ir/v/QaGZX2N0",
    "image": "https://s100.divarcdn.com/static/photo/neda/webp_thumbnail/6pxh-_HQS4ZPB4_h52nqSw/4cdce270-673a-45f5-bd11-19fce6a4e5bd.webp"
  },
  {
    "title": "هایما S7 Pro (تحویل روز سند بنام اقساط بلند مدت)",
    "subtitle": "۰ کیلومتر",
    "price": "۱,۶۰۰,۰۰۰,۰۰۰ تومان",
    "city": "تهران",
    "location": "جمال‌زاده",
    "token": "AaNyviZr",
    "url": "https://divar.ir/v/AaNyviZr",
    "image": "https://s100.divarcdn.com/static/photo/afra/webp_thumbnail/0uHOeJLJLYZx7s2ZW52NWA/ae205a76-159f-41d0-829d-95c0df223a8f.jpg.webp"
  },
  {
    "title": "سمند سورن پلاس دوگانه شرکتی/مدل1404/صفر تحویل آنی",
    "subtitle": "۰ کیلومتر",
    "price": "۱,۲۸۵,۰۰۰,۰۰۰ تومان",
    "city": "تهران",
    "location": "شهرآرا",
    "token": "AaJxiS5o",
    "url": "https://divar.ir/v/AaJxiS5o",
    "image": "https://s100.divarcdn.com/static/photo/neda/webp_thumbnail/TINyRNDVH6H6EzNxkU_c4g/4e4edce6-a46c-428e-abfd-1278c008003b.jpg.webp"
  },
  {
    "title": "فروش اقساط لوکانو ۷ لوکانو ۸ صفر",
    "subtitle": "۰ کیلومتر",
    "price": "۱۰,۰۰۰,۰۰۰ تومان",
    "city": "تهران",
    "location": "المهدی",
    "token": "QaTZIrIU",
    "url": "https://divar.ir/v/QaTZIrIU",
    "image": "https://s100.divarcdn.com/static/photo/neda/webp_thumbnail/UAmSi_7UAafSBdUa16ZI5A/c38b5e02-9825-4403-9e76-a62755866ce5.webp"
  },
  {
    "title": "دنا اتوماتیک اپشنال/دنا ۶دنده",
    "subtitle": "۰ کیلومتر",
    "price": "۱,۶۹۰,۰۰۰,۰۰۰ تومان",
    "city": "تهران",
    "location": "ستارخان",
    "token": "QaJWu0tR",
    "url": "https://divar.ir/v/QaJWu0tR",
    "image": "https://s100.divarcdn.com/static/photo/neda/webp_thumbnail/u1LmRKruj8EwcenK6FWJIg/a806c589-9061-4cb5-8f18-f7a831fb8a11.webp"
  },
  {
    "title": "کوییک gx (تحویل روز سود بانکی نقد و اقساط 36ماهه)",
    "subtitle": "۰ کیلومتر",
    "price": "۴۵۰,۰۰۰,۰۰۰ تومان",
    "city": "تهران",
    "location": "جمال‌زاده",
    "token": "wZ23ylyF",
    "url": "https://divar.ir/v/wZ23ylyF",
    "image": "https://s100.divarcdn.com/static/photo/neda/webp_thumbnail/jjILrLYyreFVE3AOvyutSw/68895283-d92c-4d1b-8efa-a2b465ece5cf.webp"
  },
  {
    "title": "سورن پلاس+ XU7P مدل 1404  تحویل روز",
    "subtitle": "۰ کیلومتر",
    "price": "۱,۱۸۵,۰۰۰,۰۰۰ تومان",
    "city": "تهران",
    "location": "شهرآرا",
    "token": "QabdFo25",
    "url": "https://divar.ir/v/QabdFo25",
    "image": "https://s100.divarcdn.com/static/photo/neda/webp_thumbnail/CpbpDHvaZEOMiOYjfg6XZg/c50eab1d-fe1f-4831-b77e-539cfc27f248.webp"
  },
  {
    "title": "فروش کرمان موتور کی ام سی جی 7",
    "subtitle": "۰ کیلومتر",
    "price": "۳,۴۰۰,۰۰۰,۰۰۰ تومان",
    "city": "تهران",
    "location": "قیام",
    "token": "QaB1DA3i",
    "url": "https://divar.ir/v/QaB1DA3i",
    "image": "https://s100.divarcdn.com/static/photo/neda/webp_thumbnail/DLWUsDypfsCp8dtJyLIYGw/f189d57a-a8c4-40f0-8b38-c96c164cbe25.webp"
  },
  {
    "title": "اکستریم VX QX",
    "subtitle": "۰ کیلومتر",
    "price": "۸,۰۰۰,۰۰۰,۰۰۰ تومان",
    "city": "تهران",
    "location": "جنت‌آباد شمالی",
    "token": "QaQOlEz4",
    "url": "https://divar.ir/v/QaQOlEz4",
    "image": "https://s100.divarcdn.com/static/photo/neda/webp_thumbnail/GZQY_rP2Li6kFtajwbx1Xg/cc310f9a-cc16-446d-bcf8-0bb639e1292f.webp"
  },
  {
    "title": "نیسان قشقایی 2025 موتور (2 لیتری )",
    "subtitle": "۰ کیلومتر",
    "price": "۵,۵۹۵,۰۰۰,۰۰۰ تومان",
    "city": "تهران",
    "location": "جماران (نیاوران)",
    "token": "QaZmHukQ",
    "url": "https://divar.ir/v/QaZmHukQ",
    "image": "https://s100.divarcdn.com/static/photo/neda/webp_thumbnail/cn285610iH_Ih-ZZrTP95Q/f5af513e-3d0d-4010-90fa-2e567fe623c1.webp"
  },
  {
    "title": "کی‌ام‌سی ایگل /kmc eagle، مدل1404",
    "subtitle": "۰ کیلومتر",
    "price": "۱,۸۰۰,۰۰۰,۰۰۰ تومان",
    "city": "تهران",
    "location": "سهروردی",
    "token": "Qa05mkEX",
    "url": "https://divar.ir/v/Qa05mkEX",
    "image": "https://s100.divarcdn.com/static/photo/neda/webp_thumbnail/yULUcZhfGZ-2EyyRxEmU7Q/c07d4080-6f2b-4876-ba8a-e93f7a59b651.webp"
  },
  {
    "title": "هایما x7اقساط بانکی/تحویل لحظه/اقساط۵ساله",
    "subtitle": "۰ کیلومتر",
    "price": "۱,۳۷۰,۰۰۰,۰۰۰,۰۰۰ تومان",
    "city": "تهران",
    "location": "جنت‌آباد جنوبی",
    "token": "QaUODhgT",
    "url": "https://divar.ir/v/QaUODhgT",
    "image": "https://s100.divarcdn.com/static/photo/neda/webp_thumbnail/L_diKHzMWtoFeXLZDGTXkw/0af2a432-57a6-40c3-b346-f86679ada948.webp"
  },
  {
    "title": "ریرا ایران خودرو ری‌ را توربو/1404و1405تحویل فوری",
    "subtitle": "۰ کیلومتر",
    "price": "۲,۳۶۵,۰۰۰,۰۰۰ تومان",
    "city": "تهران",
    "location": "شهرآرا",
    "token": "QaRi3B2p",
    "url": "https://divar.ir/v/QaRi3B2p",
    "image": "https://s100.divarcdn.com/static/photo/neda/webp_thumbnail/29QAJL6d4pe624VA9bUfkg/abe33801-c3a1-459a-8144-3f0819779aa2.webp"
  },
  {
    "title": "دیگنیتی پرایم Prime داخل مشکی*مارون/*1404صفر روز",
    "subtitle": "۰ کیلومتر",
    "price": "۳,۴۲۵,۰۰۰,۰۰۰ تومان",
    "city": "تهران",
    "location": "شهرآرا",
    "token": "QaVu5g51",
    "url": "https://divar.ir/v/QaVu5g51",
    "image": "https://s100.divarcdn.com/static/photo/neda/webp_thumbnail/iZakerAJsEeHLbw38_aaQg/7455f185-8d83-46c5-8e54-19c8d0bad57c.webp"
  },
  {
    "title": "207 پانوراما اتومات سقف شیشه ای TU5P صفر 1404",
    "subtitle": "۰ کیلومتر",
    "price": "۱,۷۷۰,۰۰۰,۰۰۰ تومان",
    "city": "تهران",
    "location": "فردوس",
    "token": "QasN6Vt0",
    "url": "https://divar.ir/v/QasN6Vt0",
    "image": "https://s100.divarcdn.com/static/photo/neda/webp_thumbnail/3q4HydGhJXu28lR9aaWujA/a1544b86-86e1-4cc4-9ee9-6d40b481f93f.webp"
  },
  {
    "title": "تویوتا لوین بنزینی ۱۲۰۰ توربو ۲۰۲۴ صفر خشک",
    "subtitle": "۰ کیلومتر",
    "price": "۴,۶۵۰,۰۰۰,۰۰۰ تومان",
    "city": "تهران",
    "location": "جنت‌آباد جنوبی",
    "token": "QandF1yc",
    "url": "https://divar.ir/v/QandF1yc",
    "image": "https://s100.divarcdn.com/static/photo/neda/webp_thumbnail/OGWRlSX-8TavKa1mWPgdqg/c619b29e-2164-4bcd-9e3f-8ae3267b2c11.webp"
  },
  {
    "title": "دنا پلاس توربو اتوماتیک آپشنال/1404و1405تحویل فوری",
    "subtitle": "۰ کیلومتر",
    "price": "۱,۸۳۵,۰۰۰,۰۰۰ تومان",
    "city": "تهران",
    "location": "شهرآرا",
    "token": "QaRSnfrT",
    "url": "https://divar.ir/v/QaRSnfrT",
    "image": "https://s100.divarcdn.com/static/photo/neda/webp_thumbnail/G4TT7DE2tdxW1oYN9PcZ-A/f0640ef7-3de1-4c9a-8c2c-8c2c7b9b1850.webp"
  },
  {
    "title": "آریزو 6 جی تی صفر / فروش نقد و اقساط بانکی",
    "subtitle": "۰ کیلومتر",
    "price": "۲,۴۰۰,۰۰۰,۰۰۰ تومان",
    "city": "تهران",
    "location": "ظفر",
    "token": "QadWHXOF",
    "url": "https://divar.ir/v/QadWHXOF",
    "image": "https://s100.divarcdn.com/static/photo/neda/webp_thumbnail/MD9YQ_3WNJDHil-69LGQSQ/63213b13-f9cc-4efb-bb0e-ba957dd119be.jpg.webp"
  },
  {
    "title": "هایما S8 اس8 تنوع رنگ *S7*S5*تحویل فوری1404و 1405",
    "subtitle": "۰ کیلومتر",
    "price": "۳,۳۹۰,۰۰۰,۰۰۰ تومان",
    "city": "تهران",
    "location": "شهرآرا",
    "token": "QaROsZv9",
    "url": "https://divar.ir/v/QaROsZv9",
    "image": "https://s100.divarcdn.com/static/photo/neda/webp_thumbnail/idlW_9zr9e9qzvHEK8K8SQ/7a358fa3-9a6a-44ea-8a7b-4e7567ac3bbe.webp"
  },
  {
    "title": "لندکروز ۲۰۲۵ صفر",
    "subtitle": "۰ کیلومتر",
    "price": "۱,۰۰۰ تومان",
    "city": "تهران",
    "location": "آجودانیه",
    "token": "QadW3RD8",
    "url": "https://divar.ir/v/QadW3RD8",
    "image": "https://s100.divarcdn.com/static/photo/neda/webp_thumbnail/_bAaz9a3WjkJaER6JmYKHQ/16998aa3-3385-4600-b37a-0af69cfe582d.webp"
  },
  {
    "title": "سمند سورن پلاس EF7 دوگانه شرکتی/*مدل1404تحویل روز",
    "subtitle": "۰ کیلومتر",
    "price": "۱,۲۶۰,۰۰۰,۰۰۰ تومان",
    "city": "تهران",
    "location": "شهرآرا",
    "token": "QaRmn6F8",
    "url": "https://divar.ir/v/QaRmn6F8",
    "image": "https://s100.divarcdn.com/static/photo/neda/webp_thumbnail/X81SvN1pAj_XkQRqdL6rHQ/39d4aae0-f402-497c-a57e-a88ff1890c46.webp"
  },
  {
    "title": "تارا اتوماتیک V4 وی4 تنوع رنگ/*مدل1404 تحویل فوری",
    "subtitle": "۰ کیلومتر",
    "price": "۱,۷۲۵,۰۰۰,۰۰۰ تومان",
    "city": "تهران",
    "location": "شهرآرا",
    "token": "QaRKp3lS",
    "url": "https://divar.ir/v/QaRKp3lS",
    "image": "https://s100.divarcdn.com/static/photo/neda/webp_thumbnail/huJM2I5exn_7WXKAuVrEnw/cb42c4ab-a0ff-40f1-94bb-fd44ea9d515b.webp"
  },
  {
    "title": "پژو۲۰۷ اتوماتیک سقف فلز صفر ۱۴۰۴",
    "subtitle": "۰ کیلومتر",
    "price": "۱,۷۹۰,۰۰۰,۰۰۰ تومان",
    "city": "تهران",
    "location": "پاسداران",
    "token": "QadSX-Jb",
    "url": "https://divar.ir/v/QadSX-Jb",
    "image": "https://s100.divarcdn.com/static/photo/neda/webp_thumbnail/FgEpcp5LyfXZSXHT6htWzQ/caaf3773-19df-495e-95fd-464b02a95207.webp"
  },
  {
    "title": "پژو207i دنده ای پانوراما TU5P ارتقا یافته/*1404روز",
    "subtitle": "۰ کیلومتر",
    "price": "۱,۴۴۵,۰۰۰,۰۰۰ تومان",
    "city": "تهران",
    "location": "شهرآرا",
    "token": "QaRWHpjZ",
    "url": "https://divar.ir/v/QaRWHpjZ",
    "image": "https://s100.divarcdn.com/static/photo/neda/webp_thumbnail/zHlGU0a9rbf2F0W58lRjag/bcd2bac1-a1e1-4ea0-9d88-212b1dd3a21c.webp"
  },
  {
    "title": "x77",
    "subtitle": "۰ کیلومتر",
    "price": "۳,۳۹۱,۰۰۰,۰۰۰ تومان",
    "city": "تهران",
    "location": "جنت‌آباد مرکزی",
    "token": "QadWnHyE",
    "url": "https://divar.ir/v/QadWnHyE",
    "image": "https://s100.divarcdn.com/static/photo/neda/webp_thumbnail/tORX1HuPx1tcA-IShG9wxg/d20320f3-d414-4dc5-9f32-8835f0c90130.webp"
  },
  {
    "title": "فروش نقد کی ام سی sr3/تحویل آنی",
    "subtitle": "۰ کیلومتر",
    "price": "۲,۶۵۰,۰۰۰,۰۰۰ تومان",
    "city": "تهران",
    "location": "سردارجنگل",
    "token": "QaGZX2N0",
    "url": "https://divar.ir/v/QaGZX2N0",
    "image": "https://s100.divarcdn.com/static/photo/neda/webp_thumbnail/6pxh-_HQS4ZPB4_h52nqSw/4cdce270-673a-45f5-bd11-19fce6a4e5bd.webp"
  },
  {
    "title": "هایما S7 Pro (تحویل روز سند بنام اقساط بلند مدت)",
    "subtitle": "۰ کیلومتر",
    "price": "۱,۶۰۰,۰۰۰,۰۰۰ تومان",
    "city": "تهران",
    "location": "جمال‌زاده",
    "token": "AaNyviZr",
    "url": "https://divar.ir/v/AaNyviZr",
    "image": "https://s100.divarcdn.com/static/photo/afra/webp_thumbnail/0uHOeJLJLYZx7s2ZW52NWA/ae205a76-159f-41d0-829d-95c0df223a8f.jpg.webp"
  },
  {
    "title": "سمند سورن پلاس دوگانه شرکتی/مدل1404/صفر تحویل آنی",
    "subtitle": "۰ کیلومتر",
    "price": "۱,۲۸۵,۰۰۰,۰۰۰ تومان",
    "city": "تهران",
    "location": "شهرآرا",
    "token": "AaJxiS5o",
    "url": "https://divar.ir/v/AaJxiS5o",
    "image": "https://s100.divarcdn.com/static/photo/neda/webp_thumbnail/TINyRNDVH6H6EzNxkU_c4g/4e4edce6-a46c-428e-abfd-1278c008003b.jpg.webp"
  },
  {
    "title": "فروش اقساط لوکانو ۷ لوکانو ۸ صفر",
    "subtitle": "۰ کیلومتر",
    "price": "۱۰,۰۰۰,۰۰۰ تومان",
    "city": "تهران",
    "location": "المهدی",
    "token": "QaTZIrIU",
    "url": "https://divar.ir/v/QaTZIrIU",
    "image": "https://s100.divarcdn.com/static/photo/neda/webp_thumbnail/UAmSi_7UAafSBdUa16ZI5A/c38b5e02-9825-4403-9e76-a62755866ce5.webp"
  },
  {
    "title": "دنا اتوماتیک اپشنال/دنا ۶دنده",
    "subtitle": "۰ کیلومتر",
    "price": "۱,۶۹۰,۰۰۰,۰۰۰ تومان",
    "city": "تهران",
    "location": "ستارخان",
    "token": "QaJWu0tR",
    "url": "https://divar.ir/v/QaJWu0tR",
    "image": "https://s100.divarcdn.com/static/photo/neda/webp_thumbnail/u1LmRKruj8EwcenK6FWJIg/a806c589-9061-4cb5-8f18-f7a831fb8a11.webp"
  },
  {
    "title": "کوییک gx (تحویل روز سود بانکی نقد و اقساط 36ماهه)",
    "subtitle": "۰ کیلومتر",
    "price": "۴۵۰,۰۰۰,۰۰۰ تومان",
    "city": "تهران",
    "location": "جمال‌زاده",
    "token": "wZ23ylyF",
    "url": "https://divar.ir/v/wZ23ylyF",
    "image": "https://s100.divarcdn.com/static/photo/neda/webp_thumbnail/jjILrLYyreFVE3AOvyutSw/68895283-d92c-4d1b-8efa-a2b465ece5cf.webp"
  }
]